Workbook

Sheet uom_category
A1: code | B1: name | C1: uuid | D1: sync_status | E1: sync_message | F1: sync_time
A2: CA00001 | B2: Count
A3: CA00002 | B3: Weight
A4: CA00003 | B4: Time
A5: CA00004 | B5: Length
A6: CA00005 | B6: Volume
A7: CA00005 | B7: Services
A8: CA00008 | B8: Sachet
A9: CA00010 | B9: Counting
A10: CA00012 | B10: Container
A11: CA00014 | B11: Container
A12: CA00016 | B12: Package
A13: CA00017 | B13: Package
A14: CA00018 | B14: Container
B15: uom_category_name

Sheet uom
A1: code | B1: name | C1: uom_category_code | D1: uom_category_name | E1: factor | F1: rounding | G1: active | H1: uomType | I1: uuid | J1: sync_status | K1: sync_message | L1: sync_time
A2: =concatenate("UM", text(A2, "00000")) | B2: Unit(s) | C2: =XLOOKUP(E2, uom_category!C:C, uom_category!B:B, "Not Found") | D2: Count | E2: 1 | F2: 0.001 | G2: true | H2: reference
A3: =concatenate("UM", text(A3, "00000")) | B3: Dozen(s) | C3: =XLOOKUP(E3, uom_category!C:C, uom_category!B:B, "Not Found") | D3: Count | E3: 0.083333333 | F3: 0.01 | G3: true | H3: bigger
A4: =concatenate("UM", text(A4, "00000")) | B4: kg | C4: =XLOOKUP(E4, uom_category!C:C, uom_category!B:B, "Not Found") | D4: Weight | E4: 1 | F4: 0.001 | G4: true | H4: reference
A5: =concatenate("UM", text(A5, "00000")) | B5: g | C5: =XLOOKUP(E5, uom_category!C:C, uom_category!B:B, "Not Found") | D5: Weight | E5: 1000 | F5: 0.01 | G5: true | H5: smaller
A6: =concatenate("UM", text(A6, "00000")) | B6: Day(s) | C6: =XLOOKUP(E6, uom_category!C:C, uom_category!B:B, "Not Found") | D6: Time | E6: 1 | F6: 0.01 | G6: true | H6: reference
A7: =concatenate("UM", text(A7, "00000")) | B7: Hour(s) | C7: =XLOOKUP(E7, uom_category!C:C, uom_category!B:B, "Not Found") | D7: Time | E7: 8 | F7: 0.01 | G7: true | H7: smaller
A8: =concatenate("UM", text(A8, "00000")) | B8: t | C8: =XLOOKUP(E8, uom_category!C:C, uom_category!B:B, "Not Found") | D8: Weight | E8: 0.001 | F8: 0.01 | G8: true | H8: bigger
A9: =concatenate("UM", text(A9, "00000")) | B9: m | C9: =XLOOKUP(E9, uom_category!C:C, uom_category!B:B, "Not Found") | D9: Length | E9: 1 | F9: 0.01 | G9: true | H9: reference
A10: =concatenate("UM", text(A10, "00000")) | B10: km | C10: =XLOOKUP(E10, uom_category!C:C, uom_category!B:B, "Not Found") | D10: Length | E10: 0.001 | F10: 0.01 | G10: true | H10: bigger
A11: =concatenate("UM", text(A11, "00000")) | B11: cm | C11: =XLOOKUP(E11, uom_category!C:C, uom_category!B:B, "Not Found") | D11: Length | E11: 100 | F11: 0.01 | G11: true | H11: smaller
A12: =concatenate("UM", text(A12, "00000")) | B12: Liter(s) | C12: =XLOOKUP(E12, uom_category!C:C, uom_category!B:B, "Not Found") | D12: Volume | E12: 1 | F12: 0.01 | G12: true | H12: reference
A13: =concatenate("UM", text(A13, "00000")) | B13: lb(s) | C13: =XLOOKUP(E13, uom_category!C:C, uom_category!B:B, "Not Found") | D13: Weight | E13: 2.20462 | F13: 0.01 | G13: true | H13: smaller
... A56: =concatenate("UM", text(A56, "00000")) | B56: Oral Vial | C56: =XLOOKUP(E56, uom_category!C:C, uom_category!B:B, "Not Found") | D56: Container | E56: 1 | F56: 0.01 | G56: true | H56: bigger

Sheet item_category
A1: code | B1: name | C1: parent_code | D1: parentName | E1: uuid | F1: sync_status | G1: sync_message | H1: sync_time
A2: =concatenate("CA", text(A2, "00000")) | B2: Product
A3: =concatenate("CA", text(A3, "00000")) | B3: Service | D3: All
A4: =concatenate("CA", text(A4, "00000")) | B4: Medical | C4: CA00002 | D4: All
A5: =concatenate("CA", text(A5, "00000")) | B5: Expenses | C5: CA00002 | D5: All
A6: =concatenate("CA", text(A6, "00000")) | B6: Internal | D6: All
A7: =concatenate("CA", text(A7, "00000")) | B7: Drug | C7: CA00002 | D7: Saleable
A8: =concatenate("CA", text(A8, "00000")) | B8: Injection | C8: CA00005 | D8: Medical
A9: =concatenate("CA", text(A9, "00000")) | B9: Saleable2 | C9: CA00001 | D9: Services
A10: =concatenate("CA", text(A10, "00000")) | B10: Software | C10: CA00001 | D10: Saleable
A11: =concatenate("CA", text(A11, "00000")) | B11: Office Furniture | C11: CA00076 | D11: Saleable
A12: =concatenate("CA", text(A12, "00000")) | B12: Counting | C12: CA00005 | D12: All
A13: =concatenate("CA", text(A13, "00000")) | B13: Consumable | D13: All
A14: =concatenate("CA", text(A14, "00000")) | B14: PoS | D14: Saleable
A15: =concatenate("CA", text(A15, "00000")) | B15: No Category Yet
A16: =concatenate("CA", text(A16, "00000")) | B16: Counting Pack | C16: CA00002
A17: =concatenate("CA", text(A17, "00000")) | B17: Counting Retail | C17: CA00002
A18: =concatenate("CA", text(A18, "00000")) | B18: Eye&Ear Drops | C18: CA00002
A19: =concatenate("CA", text(A19, "00000")) | B19: Ear Drops | C19: CA00002
A20: =concatenate("CA", text(A20, "00000")) | B20: Eye Drops | C20: CA00002
A21: =concatenate("CA", text(A21, "00000")) | B21: Infusions | C21: CA00002
A22: =concatenate("CA", text(A22, "00000")) | B22: Injections | C22: CA00002
A23: =concatenate("CA", text(A23, "00000")) | B23: Ethical Liquids | C23: CA00002
A24: =concatenate("CA", text(A24, "00000")) | B24: OTC Oral Drops | C24: CA00002
A25: =concatenate("CA", text(A25, "00000")) | B25: Powder | C25: CA00002
A26: =concatenate("CA", text(A26, "00000")) | B26: Surgicals | C26: CA00001
A27: =concatenate("CA", text(A27, "00000")) | B27: Ethical Sachets | C27: CA00002
A28: =concatenate("CA", text(A28, "00000")) | B28: OTC Sachets | C28: CA00002
A29: =concatenate("CA", text(A29, "00000")) | B29: Supermarket
A30: =concatenate("CA", text(A30, "00000")) | B30: Stationary | C30: CA00001
A31: =concatenate("CA", text(A31, "00000")) | B31: Tubes & Creams | C31: CA00005
A32: =concatenate("CA", text(A32, "00000")) | B32: OTC Liquids | C32: CA00005
A33: =concatenate("CA", text(A33, "00000")) | B33: Medical Consultation | C33: CA00002
A34: =concatenate("CA", text(A34, "00000")) | B34: Nose Drops | C34: CA00005
A35: =concatenate("CA", text(A35, "00000")) | B35: Ethical Oral Drops | C35: CA00005
A36: =concatenate("CA", text(A36, "00000")) | B36: Medical Equipments | C36: CA00001
A37: =concatenate("CA", text(A37, "00000")) | B37: item_category_name

Sheet classification
A1: code | B1: name | C1: uuid | D1: sync_status | E1: sync_message | F1: sync_time
A2: =concatenate("CA", text(A2, "00000")) | B2: All
A19: ignore | B19: classification_name

Sheet item
A1: sn | B1: name | C1: code | D1: category_id | E1: category_code | F1: item_category_name | G1: drug_code | H1: drug_name | I1: unit_price | J1: uomCode | K1: uom_name | L1: purchase_uom_code | M1: purchase_uom_name | N1: active | O1: tracking | P1: classification_code | Q1: classification_name | R1: uuid | S1: sync_status | T1: sync_message | U1: sync_time
A2: 1 | B2: Inj Fortwin | C2: =CONCATENATE("PD", TEXT(A2, "1000000")) | D2: 65 | E2: =XLOOKUP(G2, item_category!C:C, item_category!B:B, "Not Found") | F2: Injection | G2: =XLOOKUP(I2, drug!B:B, drug!A:A, "Not Found") | H2: Fortwin | I2: 1 | J2: =XLOOKUP(L2, uom!C:C, uom!B:B, "Not Found") | K2: Injection | L2: =XLOOKUP(N2, uom!C:C, uom!B:B, "Not Found") | M2: Unit(s) | N2: false | O2: none | P2: =XLOOKUP(R2, classification!C:C, classification!B:B, "Not Found") | Q2: All
A3: 2 | B3: 2.2.1 Forte Syrup | C3: =CONCATENATE("PD", TEXT(A3, "1000000")) | D3: 67 | E3: =XLOOKUP(G3, item_category!C:C, item_category!B:B, "Not Found") | F3: OTC Liquids | G3: =XLOOKUP(I3, drug!B:B, drug!A:A, "Not Found") | H3: 2 2 1 Forte Syrup | I3: 1 | J3: =XLOOKUP(L3, uom!C:C, uom!B:B, "Not Found") | K3: Unit(s) | L3: =XLOOKUP(N3, uom!C:C, uom!B:B, "Not Found") | M3: Unit(s) | N3: false | O3: none | P3: =XLOOKUP(R3, classification!C:C, classification!B:B, "Not Found") | Q3: All
A4: 3 | B4: Drawer | C4: =CONCATENATE("PD", TEXT(A4, "1000000")) | D4: 8 | E4: =XLOOKUP(G4, item_category!C:C, item_category!B:B, "Not Found") | F4: Office Furniture | G4: =XLOOKUP(I4, drug!B:B, drug!A:A, "Not Found") | H4: Drawer | I4: 3645 | J4: =XLOOKUP(L4, uom!C:C, uom!B:B, "Not Found") | K4: Unit(s) | L4: =XLOOKUP(N4, uom!C:C, uom!B:B, "Not Found") | M4: Unit(s) | N4: false | O4: none | P4: =XLOOKUP(R4, classification!C:C, classification!B:B, "Not Found") | Q4: All
A5: 4 | B5: Acepol Paracetamol Syrup | C5: =CONCATENATE("PD", TEXT(A5, "1000000")) | D5: 67 | E5: =XLOOKUP(G5, item_category!C:C, item_category!B:B, "Not Found") | F5: OTC Liquids | G5: =XLOOKUP(I5, drug!B:B, drug!A:A, "Not Found") | H5: Paracetamol | I5: 1 | J5: =XLOOKUP(L5, uom!C:C, uom!B:B, "Not Found") | K5: Unit(s) | L5: =XLOOKUP(N5, uom!C:C, uom!B:B, "Not Found") | M5: Unit(s) | N5: false | O5: none | P5: =XLOOKUP(R5, classification!C:C, classification!B:B, "Not Found") | Q5: All
A6: 5 | B6: Digoxin 250mg (X28) | C6: =CONCATENATE("PD", TEXT(A6, "1000000")) | D6: 74 | E6: =XLOOKUP(G6, item_category!C:C, item_category!B:B, "Not Found") | F6: Ethical Sachets | G6: =XLOOKUP(I6, drug!B:B, drug!A:A, "Not Found") | H6: Digoxin | I6: 1 | J6: =XLOOKUP(L6, uom!C:C, uom!B:B, "Not Found") | K6: Unit(s) | L6: =XLOOKUP(N6, uom!C:C, uom!B:B, "Not Found") | M6: Unit(s) | N6: false | O6: none | P6: =XLOOKUP(R6, classification!C:C, classification!B:B, "Not Found") | Q6: All
A7: 6 | B7: Neurogesic Extra Oint 25g | C7: =CONCATENATE("PD", TEXT(A7, "1000000")) | D7: 78 | E7: =XLOOKUP(G7, item_category!C:C, item_category!B:B, "Not Found") | F7: Tubes & Creams | G7: =XLOOKUP(I7, drug!B:B, drug!A:A, "Not Found") | H7: Neurogesic | I7: 450 | J7: =XLOOKUP(L7, uom!C:C, uom!B:B, "Not Found") | K7: Tube | L7: =XLOOKUP(N7, uom!C:C, uom!B:B, "Not Found") | M7: Tube | N7: true | O7: lot | P7: =XLOOKUP(R7, classification!C:C, classification!B:B, "Not Found") | Q7: All
A8: 7 | B8: Digoxin 250mg (x1) | C8: =CONCATENATE("PD", TEXT(A8, "1000000")) | D8: 59 | E8: =XLOOKUP(G8, item_category!C:C, item_category!B:B, "Not Found") | F8: Counting Retail | G8: =XLOOKUP(I8, drug!B:B, drug!A:A, "Not Found") | H8: Digoxin | I8: 1 | J8: =XLOOKUP(L8, uom!C:C, uom!B:B, "Not Found") | K8: Unit(s) | L8: =XLOOKUP(N8, uom!C:C, uom!B:B, "Not Found") | M8: Unit(s) | N8: false | O8: none | P8: =XLOOKUP(R8, classification!C:C, classification!B:B, "Not Found") | Q8: All
A9: 8 | B9: Conference Chair | C9: =CONCATENATE("PD", TEXT(A9, "1000000")) | D9: 8 | E9: =XLOOKUP(G9, item_category!C:C, item_category!B:B, "Not Found") | F9: Office Furniture | G9: =XLOOKUP(I9, drug!B:B, drug!A:A, "Not Found") | H9: Conference Chair | I9: 16.5 | J9: =XLOOKUP(L9, uom!C:C, uom!B:B, "Not Found") | K9: Unit(s) | L9: =XLOOKUP(N9, uom!C:C, uom!B:B, "Not Found") | M9: Unit(s) | N9: false | O9: none | P9: =XLOOKUP(R9, classification!C:C, classification!B:B, "Not Found") | Q9: All
A10: 9 | B10: Office Chair Black | C10: =CONCATENATE("PD", TEXT(A10, "1000000")) | D10: 8 | E10: =XLOOKUP(G10, item_category!C:C, item_category!B:B, "Not Found") | F10: Office Furniture | G10: =XLOOKUP(I10, drug!B:B, drug!A:A, "Not Found") | H10: Office Chair Black | I10: 12.5 | J10: =XLOOKUP(L10, uom!C:C, uom!B:B, "Not Found") | K10: Unit(s) | L10: =XLOOKUP(N10, uom!C:C, uom!B:B, "Not Found") | M10: Unit(s) | N10: false | O10: none | P10: =XLOOKUP(R10, classification!C:C, classification!B:B, "Not Found") | Q10: All
A11: 10 | B11: Corner Desk Black | C11: =CONCATENATE("PD", TEXT(A11, "1000000")) | D11: 8 | E11: =XLOOKUP(G11, item_category!C:C, item_category!B:B, "Not Found") | F11: Office Furniture | G11: =XLOOKUP(I11, drug!B:B, drug!A:A, "Not Found") | H11: Corner Desk Black | I11: 85 | J11: =XLOOKUP(L11, uom!C:C, uom!B:B, "Not Found") | K11: Unit(s) | L11: =XLOOKUP(N11, uom!C:C, uom!B:B, "Not Found") | M11: Unit(s) | N11: false | O11: none | P11: =XLOOKUP(R11, classification!C:C, classification!B:B, "Not Found") | Q11: All
A12: 11 | B12: Drawer Black | C12: =CONCATENATE("PD", TEXT(A12, "1000000")) | D12: 8 | E12: =XLOOKUP(G12, item_category!C:C, item_category!B:B, "Not Found") | F12: Office Furniture | G12: =XLOOKUP(I12, drug!B:B, drug!A:A, "Not Found") | H12: Drawer | I12: 25 | J12: =XLOOKUP(L12, uom!C:C, uom!B:B, "Not Found") | K12: Unit(s) | L12: =XLOOKUP(N12, uom!C:C, uom!B:B, "Not Found") | M12: Unit(s) | N12: false | O12: none | P12: =XLOOKUP(R12, classification!C:C, classification!B:B, "Not Found") | Q12: All
A13: 12 | B13: Desk Stand with Screen | C13: =CONCATENATE("PD", TEXT(A13, "1000000")) | D13: 8 | E13: =XLOOKUP(G13, item_category!C:C, item_category!B:B, "Not Found") | F13: Office Furniture | G13: =XLOOKUP(I13, drug!B:B, drug!A:A, "Not Found") | H13: Desk Stand With | I13: 2100 | J13: =XLOOKUP(L13, uom!C:C, uom!B:B, "Not Found") | K13: Unit(s) | L13: =XLOOKUP(N13, uom!C:C, uom!B:B, "Not Found") | M13: Unit(s) | N13: false | O13: none | P13: =XLOOKUP(R13, classification!C:C, classification!B:B, "Not Found") | Q13: All
... A678: 677 | B678: Locid Suspension | C678: =CONCATENATE("PD", TEXT(A678, "1000000")) | D678: 67 | E678: =XLOOKUP(G678, item_category!C:C, item_category!B:B, "Not Found") | F678: OTC Liquids | G678: =XLOOKUP(I678, drug!B:B, drug!A:A, "Not Found") | H678: Locid | I678: 1 | J678: =XLOOKUP(L678, uom!C:C, uom!B:B, "Not Found") | K678: Unit(s) | L678: =XLOOKUP(N678, uom!C:C, uom!B:B, "Not Found") | M678: Unit(s) | N678: false | O678: none | P678: =XLOOKUP(R678, classification!C:C, classification!B:B, "Not Found") | Q678: All
A679: 678 | B679: Magsil Syrup 100ml | C679: =CONCATENATE("PD", TEXT(A679, "1000000")) | D679: 67 | E679: =XLOOKUP(G679, item_category!C:C, item_category!B:B, "Not Found") | F679: OTC Liquids | G679: =XLOOKUP(I679, drug!B:B, drug!A:A, "Not Found") | I679: 1 | J679: =XLOOKUP(L679, uom!C:C, uom!B:B, "Not Found") | K679: Unit(s) | L679: =XLOOKUP(N679, uom!C:C, uom!B:B, "Not Found") | M679: Unit(s) | N679: false | O679: none | P679: =XLOOKUP(R679, classification!C:C, classification!B:B, "Not Found") | Q679: All
A680: 679 | B680: Magsil Syrup 190ml | C680: =CONCATENATE("PD", TEXT(A680, "1000000")) | D680: 67 | E680: =XLOOKUP(G680, item_category!C:C, item_category!B:B, "Not Found") | F680: OTC Liquids | G680: =XLOOKUP(I680, drug!B:B, drug!A:A, "Not Found") | I680: 1 | J680: =XLOOKUP(L680, uom!C:C, uom!B:B, "Not Found") | K680: Unit(s) | L680: =XLOOKUP(N680, uom!C:C, uom!B:B, "Not Found") | M680: Unit(s) | N680: false | O680: none | P680: =XLOOKUP(R680, classification!C:C, classification!B:B, "Not Found") | Q680: All
A681: 680 | B681: Megacid Suspension | C681: =CONCATENATE("PD", TEXT(A681, "1000000")) | D681: 67 | E681: =XLOOKUP(G681, item_category!C:C, item_category!B:B, "Not Found") | F681: OTC Liquids | G681: =XLOOKUP(I681, drug!B:B, drug!A:A, "Not Found") | I681: 1 | J681: =XLOOKUP(L681, uom!C:C, uom!B:B, "Not Found") | K681: Unit(s) | L681: =XLOOKUP(N681, uom!C:C, uom!B:B, "Not Found") | M681: Unit(s) | N681: false | O681: none | P681: =XLOOKUP(R681, classification!C:C, classification!B:B, "Not Found") | Q681: All
A682: 681 | B682: peptomag usp 200ml | C682: =CONCATENATE("PD", TEXT(A682, "1000000")) | D682: 67 | E682: =XLOOKUP(G682, item_category!C:C, item_category!B:B, "Not Found") | F682: OTC Liquids | G682: =XLOOKUP(I682, drug!B:B, drug!A:A, "Not Found") | I682: 1 | J682: =XLOOKUP(L682, uom!C:C, uom!B:B, "Not Found") | K682: Unit(s) | L682: =XLOOKUP(N682, uom!C:C, uom!B:B, "Not Found") | M682: Unit(s) | N682: false | O682: none | P682: =XLOOKUP(R682, classification!C:C, classification!B:B, "Not Found") | Q682: All
A683: 682 | B683: polycil antacid suspension | C683: =CONCATENATE("PD", TEXT(A683, "1000000")) | D683: 67 | E683: =XLOOKUP(G683, item_category!C:C, item_category!B:B, "Not Found") | F683: OTC Liquids | G683: =XLOOKUP(I683, drug!B:B, drug!A:A, "Not Found") | I683: 1 | J683: =XLOOKUP(L683, uom!C:C, uom!B:B, "Not Found") | K683: Unit(s) | L683: =XLOOKUP(N683, uom!C:C, uom!B:B, "Not Found") | M683: Unit(s) | N683: false | O683: none | P683: =XLOOKUP(R683, classification!C:C, classification!B:B, "Not Found") | Q683: All
A684: 683 | B684: Polycrol Gel | C684: =CONCATENATE("PD", TEXT(A684, "1000000")) | D684: 67 | E684: =XLOOKUP(G684, item_category!C:C, item_category!B:B, "Not Found") | F684: OTC Liquids | G684: =XLOOKUP(I684, drug!B:B, drug!A:A, "Not Found") | I684: 1 | J684: =XLOOKUP(L684, uom!C:C, uom!B:B, "Not Found") | K684: Unit(s) | L684: =XLOOKUP(N684, uom!C:C, uom!B:B, "Not Found") | M684: Unit(s) | N684: false | O684: none | P684: =XLOOKUP(R684, classification!C:C, classification!B:B, "Not Found") | Q684: All
A685: 684 | B685: Polyfort Suspension | C685: =CONCATENATE("PD", TEXT(A685, "1000000")) | D685: 67 | E685: =XLOOKUP(G685, item_category!C:C, item_category!B:B, "Not Found") | F685: OTC Liquids | G685: =XLOOKUP(I685, drug!B:B, drug!A:A, "Not Found") | H685: Polyfort | I685: 1 | J685: =XLOOKUP(L685, uom!C:C, uom!B:B, "Not Found") | K685: Unit(s) | L685: =XLOOKUP(N685, uom!C:C, uom!B:B, "Not Found") | M685: Unit(s) | N685: false | O685: none | P685: =XLOOKUP(R685, classification!C:C, classification!B:B, "Not Found") | Q685: All
A686: 685 | B686: Recler Gel | C686: =CONCATENATE("PD", TEXT(A686, "1000000")) | D686: 67 | E686: =XLOOKUP(G686, item_category!C:C, item_category!B:B, "Not Found") | F686: OTC Liquids | G686: =XLOOKUP(I686, drug!B:B, drug!A:A, "Not Found") | I686: 1 | J686: =XLOOKUP(L686, uom!C:C, uom!B:B, "Not Found") | K686: Unit(s) | L686: =XLOOKUP(N686, uom!C:C, uom!B:B, "Not Found") | M686: Unit(s) | N686: false | O686: none | P686: =XLOOKUP(R686, classification!C:C, classification!B:B, "Not Found") | Q686: All
A687: 686 | B687: Relcer gel Antacid susp | C687: =CONCATENATE("PD", TEXT(A687, "1000000")) | D687: 67 | E687: =XLOOKUP(G687, item_category!C:C, item_category!B:B, "Not Found") | F687: OTC Liquids | G687: =XLOOKUP(I687, drug!B:B, drug!A:A, "Not Found") | I687: 1 | J687: =XLOOKUP(L687, uom!C:C, uom!B:B, "Not Found") | K687: Unit(s) | L687: =XLOOKUP(N687, uom!C:C, uom!B:B, "Not Found") | M687: Unit(s) | N687: false | O687: none | P687: =XLOOKUP(R687, classification!C:C, classification!B:B, "Not Found") | Q687: All
A688: 687 | B688: Rulox Suspension | C688: =CONCATENATE("PD", TEXT(A688, "1000000")) | D688: 67 | E688: =XLOOKUP(G688, item_category!C:C, item_category!B:B, "Not Found") | F688: OTC Liquids | G688: =XLOOKUP(I688, drug!B:B, drug!A:A, "Not Found") | I688: 1 | J688: =XLOOKUP(L688, uom!C:C, uom!B:B, "Not Found") | K688: Unit(s) | L688: =XLOOKUP(N688, uom!C:C, uom!B:B, "Not Found") | M688: Unit(s) | N688: false | O688: none | P688: =XLOOKUP(R688, classification!C:C, classification!B:B, "Not Found") | Q688: All
A689: 688 | B689: De - Shalom Anti Diarrhoea | C689: =CONCATENATE("PD", TEXT(A689, "1000000")) | D689: 67 | E689: =XLOOKUP(G689, item_category!C:C, item_category!B:B, "Not Found") | F689: OTC Liquids | G689: =XLOOKUP(I689, drug!B:B, drug!A:A, "Not Found") | I689: 1 | J689: =XLOOKUP(L689, uom!C:C, uom!B:B, "Not Found") | K689: Unit(s) | L689: =XLOOKUP(N689, uom!C:C, uom!B:B, "Not Found") | M689: Unit(s) | N689: false | O689: none | P689: =XLOOKUP(R689, classification!C:C, classification!B:B, "Not Found") | Q689: All
A690: 689 | B690: Benzyl Benzoate 100ml | C690: =CONCATENATE("PD", TEXT(A690, "1000000")) | D690: 67 | E690: =XLOOKUP(G690, item_category!C:C, item_category!B:B, "Not Found") | F690: OTC Liquids | G690: =XLOOKUP(I690, drug!B:B, drug!A:A, "Not Found") | H690: Benzyl benzoate | I690: 1 | J690: =XLOOKUP(L690, uom!C:C, uom!B:B, "Not Found") | K690: Unit(s) | L690: =XLOOKUP(N690, uom!C:C, uom!B:B, "Not Found") | M690: Unit(s) | N690: false | O690: none | P690: =XLOOKUP(R690, classification!C:C, classification!B:B, "Not Found") | Q690: All
A691: 690 | B691: Bromex Syrup | C691: =CONCATENATE("PD", TEXT(A691, "1000000")) | D691: 67 | E691: =XLOOKUP(G691, item_category!C:C, item_category!B:B, "Not Found") | F691: OTC Liquids | G691: =XLOOKUP(I691, drug!B:B, drug!A:A, "Not Found") | I691: 1 | J691: =XLOOKUP(L691, uom!C:C, uom!B:B, "Not Found") | K691: Unit(s) | L691: =XLOOKUP(N691, uom!C:C, uom!B:B, "Not Found") | M691: Unit(s) | N691: false | O691: none | P691: =XLOOKUP(R691, classification!C:C, classification!B:B, "Not Found") | Q691: All
A692: 691 | B692: cefamor Syrup 250mg | C692: =CONCATENATE("PD", TEXT(A692, "1000000")) | D692: 67 | E692: =XLOOKUP(G692, item_category!C:C, item_category!B:B, "Not Found") | F692: OTC Liquids | G692: =XLOOKUP(I692, drug!B:B, drug!A:A, "Not Found") | I692: 1 | J692: =XLOOKUP(L692, uom!C:C, uom!B:B, "Not Found") | K692: Unit(s) | L692: =XLOOKUP(N692, uom!C:C, uom!B:B, "Not Found") | M692: Unit(s) | N692: false | O692: none | P692: =XLOOKUP(R692, classification!C:C, classification!B:B, "Not Found") | Q692: All
A693: 692 | B693: Fivarex Syrup | C693: =CONCATENATE("PD", TEXT(A693, "1000000")) | D693: 67 | E693: =XLOOKUP(G693, item_category!C:C, item_category!B:B, "Not Found") | F693: OTC Liquids | G693: =XLOOKUP(I693, drug!B:B, drug!A:A, "Not Found") | I693: 1 | J693: =XLOOKUP(L693, uom!C:C, uom!B:B, "Not Found") | K693: Unit(s) | L693: =XLOOKUP(N693, uom!C:C, uom!B:B, "Not Found") | M693: Unit(s) | N693: false | O693: none | P693: =XLOOKUP(R693, classification!C:C, classification!B:B, "Not Found") | Q693: All
A694: 693 | B694: Moko Benzyl Benzoate 100ml | C694: =CONCATENATE("PD", TEXT(A694, "1000000")) | D694: 67 | E694: =XLOOKUP(G694, item_category!C:C, item_category!B:B, "Not Found") | F694: OTC Liquids | G694: =XLOOKUP(I694, drug!B:B, drug!A:A, "Not Found") | H694: Benzyl benzoate | I694: 1 | J694: =XLOOKUP(L694, uom!C:C, uom!B:B, "Not Found") | K694: Unit(s) | L694: =XLOOKUP(N694, uom!C:C, uom!B:B, "Not Found") | M694: Unit(s) | N694: false | O694: none | P694: =XLOOKUP(R694, classification!C:C, classification!B:B, "Not Found") | Q694: All
A695: 694 | B695: Moko quinine syr | C695: =CONCATENATE("PD", TEXT(A695, "1000000")) | D695: 67 | E695: =XLOOKUP(G695, item_category!C:C, item_category!B:B, "Not Found") | F695: OTC Liquids | G695: =XLOOKUP(I695, drug!B:B, drug!A:A, "Not Found") | H695: Quinine | I695: 1 | J695: =XLOOKUP(L695, uom!C:C, uom!B:B, "Not Found") | K695: Unit(s) | L695: =XLOOKUP(N695, uom!C:C, uom!B:B, "Not Found") | M695: Unit(s) | N695: false | O695: none | P695: =XLOOKUP(R695, classification!C:C, classification!B:B, "Not Found") | Q695: All
A696: 695 | B696: Daily Living Bitters | C696: =CONCATENATE("PD", TEXT(A696, "1000000")) | D696: 67 | E696: =XLOOKUP(G696, item_category!C:C, item_category!B:B, "Not Found") | F696: OTC Liquids | G696: =XLOOKUP(I696, drug!B:B, drug!A:A, "Not Found") | I696: 1 | J696: =XLOOKUP(L696, uom!C:C, uom!B:B, "Not Found") | K696: Unit(s) | L696: =XLOOKUP(N696, uom!C:C, uom!B:B, "Not Found") | M696: Unit(s) | N696: false | O696: none | P696: =XLOOKUP(R696, classification!C:C, classification!B:B, "Not Found") | Q696: All
A697: 696 | B697: Jawasil Suspension 100ml | C697: =CONCATENATE("PD", TEXT(A697, "1000000")) | D697: 67 | E697: =XLOOKUP(G697, item_category!C:C, item_category!B:B, "Not Found") | F697: OTC Liquids | G697: =XLOOKUP(I697, drug!B:B, drug!A:A, "Not Found") | I697: 600 | J697: =XLOOKUP(L697, uom!C:C, uom!B:B, "Not Found") | K697: Suspension Bottle | L697: =XLOOKUP(N697, uom!C:C, uom!B:B, "Not Found") | M697: Suspension Bottle | N697: true | O697: lot | P697: =XLOOKUP(R697, classification!C:C, classification!B:B, "Not Found") | Q697: All
A698: 697 | B698: Gestid Suspension 100ml | C698: =CONCATENATE("PD", TEXT(A698, "1000000")) | D698: 67 | E698: =XLOOKUP(G698, item_category!C:C, item_category!B:B, "Not Found") | F698: OTC Liquids | G698: =XLOOKUP(I698, drug!B:B, drug!A:A, "Not Found") | H698: Gestid | I698: 500 | J698: =XLOOKUP(L698, uom!C:C, uom!B:B, "Not Found") | K698: Syrup Bottle | L698: =XLOOKUP(N698, uom!C:C, uom!B:B, "Not Found") | M698: Syrup Bottle | N698: true | O698: lot | P698: =XLOOKUP(R698, classification!C:C, classification!B:B, "Not Found") | Q698: All
A699: 698 | B699: Evans Swedish Bitters | C699: =CONCATENATE("PD", TEXT(A699, "1000000")) | D699: 67 | E699: =XLOOKUP(G699, item_category!C:C, item_category!B:B, "Not Found") | F699: OTC Liquids | G699: =XLOOKUP(I699, drug!B:B, drug!A:A, "Not Found") | I699: 1 | J699: =XLOOKUP(L699, uom!C:C, uom!B:B, "Not Found") | K699: Unit(s) | L699: =XLOOKUP(N699, uom!C:C, uom!B:B, "Not Found") | M699: Unit(s) | N699: false | O699: none | P699: =XLOOKUP(R699, classification!C:C, classification!B:B, "Not Found") | Q699: All
A700: 699 | B700: Swedish Bitters (Imported) | C700: =CONCATENATE("PD", TEXT(A700, "1000000")) | D700: 67 | E700: =XLOOKUP(G700, item_category!C:C, item_category!B:B, "Not Found") | F700: OTC Liquids | G700: =XLOOKUP(I700, drug!B:B, drug!A:A, "Not Found") | I700: 1 | J700: =XLOOKUP(L700, uom!C:C, uom!B:B, "Not Found") | K700: Unit(s) | L700: =XLOOKUP(N700, uom!C:C, uom!B:B, "Not Found") | M700: Unit(s) | N700: false | O700: none | P700: =XLOOKUP(R700, classification!C:C, classification!B:B, "Not Found") | Q700: All
A701: 700 | B701: Amciron Tonic | C701: =CONCATENATE("PD", TEXT(A701, "1000000")) | D701: 67 | E701: =XLOOKUP(G701, item_category!C:C, item_category!B:B, "Not Found") | F701: OTC Liquids | G701: =XLOOKUP(I701, drug!B:B, drug!A:A, "Not Found") | I701: 1 | J701: =XLOOKUP(L701, uom!C:C, uom!B:B, "Not Found") | K701: Unit(s) | L701: =XLOOKUP(N701, uom!C:C, uom!B:B, "Not Found") | M701: Unit(s) | N701: false | O701: none | P701: =XLOOKUP(R701, classification!C:C, classification!B:B, "Not Found") | Q701: All
A702: 701 | B702: Astymin Tonic 110ml | C702: =CONCATENATE("PD", TEXT(A702, "1000000")) | D702: 67 | E702: =XLOOKUP(G702, item_category!C:C, item_category!B:B, "Not Found") | F702: OTC Liquids | G702: =XLOOKUP(I702, drug!B:B, drug!A:A, "Not Found") | I702: 1 | J702: =XLOOKUP(L702, uom!C:C, uom!B:B, "Not Found") | K702: Unit(s) | L702: =XLOOKUP(N702, uom!C:C, uom!B:B, "Not Found") | M702: Unit(s) | N702: false | O702: none | P702: =XLOOKUP(R702, classification!C:C, classification!B:B, "Not Found") | Q702: All
A703: 702 | B703: Bentonic Tonic | C703: =CONCATENATE("PD", TEXT(A703, "1000000")) | D703: 67 | E703: =XLOOKUP(G703, item_category!C:C, item_category!B:B, "Not Found") | F703: OTC Liquids | G703: =XLOOKUP(I703, drug!B:B, drug!A:A, "Not Found") | I703: 1 | J703: =XLOOKUP(L703, uom!C:C, uom!B:B, "Not Found") | K703: Unit(s) | L703: =XLOOKUP(N703, uom!C:C, uom!B:B, "Not Found") | M703: Unit(s) | N703: false | O703: none | P703: =XLOOKUP(R703, classification!C:C, classification!B:B, "Not Found") | Q703: All
A704: 703 | B704: Biotonic Plus Bood Tonic 200ml | C704: =CONCATENATE("PD", TEXT(A704, "1000000")) | D704: 67 | E704: =XLOOKUP(G704, item_category!C:C, item_category!B:B, "Not Found") | F704: OTC Liquids | G704: =XLOOKUP(I704, drug!B:B, drug!A:A, "Not Found") | I704: 1 | J704: =XLOOKUP(L704, uom!C:C, uom!B:B, "Not Found") | K704: Unit(s) | L704: =XLOOKUP(N704, uom!C:C, uom!B:B, "Not Found") | M704: Unit(s) | N704: false | O704: none | P704: =XLOOKUP(R704, classification!C:C, classification!B:B, "Not Found") | Q704: All
A705: 704 | B705: Biotonic Tonic B/S | C705: =CONCATENATE("PD", TEXT(A705, "1000000")) | D705: 67 | E705: =XLOOKUP(G705, item_category!C:C, item_category!B:B, "Not Found") | F705: OTC Liquids | G705: =XLOOKUP(I705, drug!B:B, drug!A:A, "Not Found") | I705: 1 | J705: =XLOOKUP(L705, uom!C:C, uom!B:B, "Not Found") | K705: Unit(s) | L705: =XLOOKUP(N705, uom!C:C, uom!B:B, "Not Found") | M705: Unit(s) | N705: false | O705: none | P705: =XLOOKUP(R705, classification!C:C, classification!B:B, "Not Found") | Q705: All
A706: 705 | B706: Biotonic Tonic M/S | C706: =CONCATENATE("PD", TEXT(A706, "1000000")) | D706: 67 | E706: =XLOOKUP(G706, item_category!C:C, item_category!B:B, "Not Found") | F706: OTC Liquids | G706: =XLOOKUP(I706, drug!B:B, drug!A:A, "Not Found") | I706: 1 | J706: =XLOOKUP(L706, uom!C:C, uom!B:B, "Not Found") | K706: Unit(s) | L706: =XLOOKUP(N706, uom!C:C, uom!B:B, "Not Found") | M706: Unit(s) | N706: false | O706: none | P706: =XLOOKUP(R706, classification!C:C, classification!B:B, "Not Found") | Q706: All
A707: 706 | B707: Biotonic Tonic S/S | C707: =CONCATENATE("PD", TEXT(A707, "1000000")) | D707: 67 | E707: =XLOOKUP(G707, item_category!C:C, item_category!B:B, "Not Found") | F707: OTC Liquids | G707: =XLOOKUP(I707, drug!B:B, drug!A:A, "Not Found") | I707: 1 | J707: =XLOOKUP(L707, uom!C:C, uom!B:B, "Not Found") | K707: Unit(s) | L707: =XLOOKUP(N707, uom!C:C, uom!B:B, "Not Found") | M707: Unit(s) | N707: false | O707: none | P707: =XLOOKUP(R707, classification!C:C, classification!B:B, "Not Found") | Q707: All
A708: 707 | B708: Bloodtone | C708: =CONCATENATE("PD", TEXT(A708, "1000000")) | D708: 67 | E708: =XLOOKUP(G708, item_category!C:C, item_category!B:B, "Not Found") | F708: OTC Liquids | G708: =XLOOKUP(I708, drug!B:B, drug!A:A, "Not Found") | I708: 1 | J708: =XLOOKUP(L708, uom!C:C, uom!B:B, "Not Found") | K708: Unit(s) | L708: =XLOOKUP(N708, uom!C:C, uom!B:B, "Not Found") | M708: Unit(s) | N708: false | O708: none | P708: =XLOOKUP(R708, classification!C:C, classification!B:B, "Not Found") | Q708: All
A709: 708 | B709: Build Up Blood Tonic | C709: =CONCATENATE("PD", TEXT(A709, "1000000")) | D709: 67 | E709: =XLOOKUP(G709, item_category!C:C, item_category!B:B, "Not Found") | F709: OTC Liquids | G709: =XLOOKUP(I709, drug!B:B, drug!A:A, "Not Found") | I709: 1 | J709: =XLOOKUP(L709, uom!C:C, uom!B:B, "Not Found") | K709: Unit(s) | L709: =XLOOKUP(N709, uom!C:C, uom!B:B, "Not Found") | M709: Unit(s) | N709: false | O709: none | P709: =XLOOKUP(R709, classification!C:C, classification!B:B, "Not Found") | Q709: All
A710: 709 | B710: Bunto Tonic MS | C710: =CONCATENATE("PD", TEXT(A710, "1000000")) | D710: 67 | E710: =XLOOKUP(G710, item_category!C:C, item_category!B:B, "Not Found") | F710: OTC Liquids | G710: =XLOOKUP(I710, drug!B:B, drug!A:A, "Not Found") | I710: 1 | J710: =XLOOKUP(L710, uom!C:C, uom!B:B, "Not Found") | K710: Unit(s) | L710: =XLOOKUP(N710, uom!C:C, uom!B:B, "Not Found") | M710: Unit(s) | N710: false | O710: none | P710: =XLOOKUP(R710, classification!C:C, classification!B:B, "Not Found") | Q710: All
A711: 710 | B711: Care On Tonic 1 litre | C711: =CONCATENATE("PD", TEXT(A711, "1000000")) | D711: 67 | E711: =XLOOKUP(G711, item_category!C:C, item_category!B:B, "Not Found") | F711: OTC Liquids | G711: =XLOOKUP(I711, drug!B:B, drug!A:A, "Not Found") | H711: Ca | I711: 1 | J711: =XLOOKUP(L711, uom!C:C, uom!B:B, "Not Found") | K711: Unit(s) | L711: =XLOOKUP(N711, uom!C:C, uom!B:B, "Not Found") | M711: Unit(s) | N711: false | O711: none | P711: =XLOOKUP(R711, classification!C:C, classification!B:B, "Not Found") | Q711: All
A712: 711 | B712: Care on tonic 200ml | C712: =CONCATENATE("PD", TEXT(A712, "1000000")) | D712: 67 | E712: =XLOOKUP(G712, item_category!C:C, item_category!B:B, "Not Found") | F712: OTC Liquids | G712: =XLOOKUP(I712, drug!B:B, drug!A:A, "Not Found") | H712: Ca | I712: 1 | J712: =XLOOKUP(L712, uom!C:C, uom!B:B, "Not Found") | K712: Unit(s) | L712: =XLOOKUP(N712, uom!C:C, uom!B:B, "Not Found") | M712: Unit(s) | N712: false | O712: none | P712: =XLOOKUP(R712, classification!C:C, classification!B:B, "Not Found") | Q712: All
A713: 712 | B713: Care On Tonic S/S | C713: =CONCATENATE("PD", TEXT(A713, "1000000")) | D713: 67 | E713: =XLOOKUP(G713, item_category!C:C, item_category!B:B, "Not Found") | F713: OTC Liquids | G713: =XLOOKUP(I713, drug!B:B, drug!A:A, "Not Found") | H713: Ca | I713: 1 | J713: =XLOOKUP(L713, uom!C:C, uom!B:B, "Not Found") | K713: Unit(s) | L713: =XLOOKUP(N713, uom!C:C, uom!B:B, "Not Found") | M713: Unit(s) | N713: false | O713: none | P713: =XLOOKUP(R713, classification!C:C, classification!B:B, "Not Found") | Q713: All
A714: 713 | B714: Metformin Glucophage 500mg (X10) | C714: =CONCATENATE("PD", TEXT(A714, "1000000")) | D714: 1 | E714: =XLOOKUP(G714, item_category!C:C, item_category!B:B, "Not Found") | F714: All | G714: =XLOOKUP(I714, drug!B:B, drug!A:A, "Not Found") | H714: Metformin | I714: 850 | J714: =XLOOKUP(L714, uom!C:C, uom!B:B, "Not Found") | K714: Sachet (X20) | L714: =XLOOKUP(N714, uom!C:C, uom!B:B, "Not Found") | M714: Sachet (X20) | N714: true | O714: lot | P714: =XLOOKUP(R714, classification!C:C, classification!B:B, "Not Found") | Q714: All
A715: 714 | B715: Cyprigold Tonic M/S | C715: =CONCATENATE("PD", TEXT(A715, "1000000")) | D715: 67 | E715: =XLOOKUP(G715, item_category!C:C, item_category!B:B, "Not Found") | F715: OTC Liquids | G715: =XLOOKUP(I715, drug!B:B, drug!A:A, "Not Found") | I715: 1 | J715: =XLOOKUP(L715, uom!C:C, uom!B:B, "Not Found") | K715: Unit(s) | L715: =XLOOKUP(N715, uom!C:C, uom!B:B, "Not Found") | M715: Unit(s) | N715: false | O715: none | P715: =XLOOKUP(R715, classification!C:C, classification!B:B, "Not Found") | Q715: All
A716: 715 | B716: Daravit Family Tonic | C716: =CONCATENATE("PD", TEXT(A716, "1000000")) | D716: 67 | E716: =XLOOKUP(G716, item_category!C:C, item_category!B:B, "Not Found") | F716: OTC Liquids | G716: =XLOOKUP(I716, drug!B:B, drug!A:A, "Not Found") | H716: Vit | I716: 1 | J716: =XLOOKUP(L716, uom!C:C, uom!B:B, "Not Found") | K716: Unit(s) | L716: =XLOOKUP(N716, uom!C:C, uom!B:B, "Not Found") | M716: Unit(s) | N716: false | O716: none | P716: =XLOOKUP(R716, classification!C:C, classification!B:B, "Not Found") | Q716: All
A717: 716 | B717: Daravit Tonic 200ml | C717: =CONCATENATE("PD", TEXT(A717, "1000000")) | D717: 67 | E717: =XLOOKUP(G717, item_category!C:C, item_category!B:B, "Not Found") | F717: OTC Liquids | G717: =XLOOKUP(I717, drug!B:B, drug!A:A, "Not Found") | H717: Vit | I717: 1 | J717: =XLOOKUP(L717, uom!C:C, uom!B:B, "Not Found") | K717: Unit(s) | L717: =XLOOKUP(N717, uom!C:C, uom!B:B, "Not Found") | M717: Unit(s) | N717: false | O717: none | P717: =XLOOKUP(R717, classification!C:C, classification!B:B, "Not Found") | Q717: All
A718: 717 | B718: Cyprigold Tonic 100ml | C718: =CONCATENATE("PD", TEXT(A718, "1000000")) | D718: 67 | E718: =XLOOKUP(G718, item_category!C:C, item_category!B:B, "Not Found") | F718: OTC Liquids | G718: =XLOOKUP(I718, drug!B:B, drug!A:A, "Not Found") | I718: 1 | J718: =XLOOKUP(L718, uom!C:C, uom!B:B, "Not Found") | K718: Syrup Bottle | L718: =XLOOKUP(N718, uom!C:C, uom!B:B, "Not Found") | M718: Syrup Bottle | N718: false | O718: lot | P718: =XLOOKUP(R718, classification!C:C, classification!B:B, "Not Found") | Q718: All
A719: 718 | B719: Clotrimazole Vaginal 100mg | C719: =CONCATENATE("PD", TEXT(A719, "1000000")) | D719: 1 | E719: =XLOOKUP(G719, item_category!C:C, item_category!B:B, "Not Found") | F719: All | G719: =XLOOKUP(I719, drug!B:B, drug!A:A, "Not Found") | H719: Clotrimazole | I719: 500 | J719: =XLOOKUP(L719, uom!C:C, uom!B:B, "Not Found") | K719: Sachet (X6) | L719: =XLOOKUP(N719, uom!C:C, uom!B:B, "Not Found") | M719: Sachet (X6) | N719: true | O719: lot | P719: =XLOOKUP(R719, classification!C:C, classification!B:B, "Not Found") | Q719: All
A720: 719 | B720: Darkins Heamoglobin Tonic | C720: =CONCATENATE("PD", TEXT(A720, "1000000")) | D720: 67 | E720: =XLOOKUP(G720, item_category!C:C, item_category!B:B, "Not Found") | F720: OTC Liquids | G720: =XLOOKUP(I720, drug!B:B, drug!A:A, "Not Found") | I720: 1 | J720: =XLOOKUP(L720, uom!C:C, uom!B:B, "Not Found") | K720: Unit(s) | L720: =XLOOKUP(N720, uom!C:C, uom!B:B, "Not Found") | M720: Unit(s) | N720: false | O720: none | P720: =XLOOKUP(R720, classification!C:C, classification!B:B, "Not Found") | Q720: All
A721: 720 | B721: Detonic Tonic 200ml | C721: =CONCATENATE("PD", TEXT(A721, "1000000")) | D721: 67 | E721: =XLOOKUP(G721, item_category!C:C, item_category!B:B, "Not Found") | F721: OTC Liquids | G721: =XLOOKUP(I721, drug!B:B, drug!A:A, "Not Found") | I721: 1 | J721: =XLOOKUP(L721, uom!C:C, uom!B:B, "Not Found") | K721: Unit(s) | L721: =XLOOKUP(N721, uom!C:C, uom!B:B, "Not Found") | M721: Unit(s) | N721: false | O721: none | P721: =XLOOKUP(R721, classification!C:C, classification!B:B, "Not Found") | Q721: All
A722: 721 | B722: Dexampple Tonic | C722: =CONCATENATE("PD", TEXT(A722, "1000000")) | D722: 67 | E722: =XLOOKUP(G722, item_category!C:C, item_category!B:B, "Not Found") | F722: OTC Liquids | G722: =XLOOKUP(I722, drug!B:B, drug!A:A, "Not Found") | I722: 1 | J722: =XLOOKUP(L722, uom!C:C, uom!B:B, "Not Found") | K722: Unit(s) | L722: =XLOOKUP(N722, uom!C:C, uom!B:B, "Not Found") | M722: Unit(s) | N722: false | O722: none | P722: =XLOOKUP(R722, classification!C:C, classification!B:B, "Not Found") | Q722: All
A723: 722 | B723: Bunto Tonic S/S | C723: =CONCATENATE("PD", TEXT(A723, "1000000")) | D723: 67 | E723: =XLOOKUP(G723, item_category!C:C, item_category!B:B, "Not Found") | F723: OTC Liquids | G723: =XLOOKUP(I723, drug!B:B, drug!A:A, "Not Found") | I723: 450 | J723: =XLOOKUP(L723, uom!C:C, uom!B:B, "Not Found") | K723: Syrup Bottle | L723: =XLOOKUP(N723, uom!C:C, uom!B:B, "Not Found") | M723: Syrup Bottle | N723: true | O723: lot | P723: =XLOOKUP(R723, classification!C:C, classification!B:B, "Not Found") | Q723: All
A724: 723 | B724: Chemiron Tonic (200ml) | C724: =CONCATENATE("PD", TEXT(A724, "1000000")) | D724: 67 | E724: =XLOOKUP(G724, item_category!C:C, item_category!B:B, "Not Found") | F724: OTC Liquids | G724: =XLOOKUP(I724, drug!B:B, drug!A:A, "Not Found") | I724: 650 | J724: =XLOOKUP(L724, uom!C:C, uom!B:B, "Not Found") | K724: Syrup Bottle | L724: =XLOOKUP(N724, uom!C:C, uom!B:B, "Not Found") | M724: Syrup Bottle | N724: true | O724: lot | P724: =XLOOKUP(R724, classification!C:C, classification!B:B, "Not Found") | Q724: All
A725: 724 | B725: Astyfer Tonic 200ml | C725: =CONCATENATE("PD", TEXT(A725, "1000000")) | D725: 67 | E725: =XLOOKUP(G725, item_category!C:C, item_category!B:B, "Not Found") | F725: OTC Liquids | G725: =XLOOKUP(I725, drug!B:B, drug!A:A, "Not Found") | I725: 1250 | J725: =XLOOKUP(L725, uom!C:C, uom!B:B, "Not Found") | K725: Syrup Bottle | L725: =XLOOKUP(N725, uom!C:C, uom!B:B, "Not Found") | M725: Syrup Bottle | N725: true | O725: lot | P725: =XLOOKUP(R725, classification!C:C, classification!B:B, "Not Found") | Q725: All
A726: 725 | B726: Dr Nelsons Blood Tonic | C726: =CONCATENATE("PD", TEXT(A726, "1000000")) | D726: 67 | E726: =XLOOKUP(G726, item_category!C:C, item_category!B:B, "Not Found") | F726: OTC Liquids | G726: =XLOOKUP(I726, drug!B:B, drug!A:A, "Not Found") | I726: 1 | J726: =XLOOKUP(L726, uom!C:C, uom!B:B, "Not Found") | K726: Unit(s) | L726: =XLOOKUP(N726, uom!C:C, uom!B:B, "Not Found") | M726: Unit(s) | N726: false | O726: none | P726: =XLOOKUP(R726, classification!C:C, classification!B:B, "Not Found") | Q726: All
A727: 726 | B727: Eleron Tonic | C727: =CONCATENATE("PD", TEXT(A727, "1000000")) | D727: 67 | E727: =XLOOKUP(G727, item_category!C:C, item_category!B:B, "Not Found") | F727: OTC Liquids | G727: =XLOOKUP(I727, drug!B:B, drug!A:A, "Not Found") | I727: 1 | J727: =XLOOKUP(L727, uom!C:C, uom!B:B, "Not Found") | K727: Unit(s) | L727: =XLOOKUP(N727, uom!C:C, uom!B:B, "Not Found") | M727: Unit(s) | N727: false | O727: none | P727: =XLOOKUP(R727, classification!C:C, classification!B:B, "Not Found") | Q727: All
A728: 727 | B728: Everyday Tonic | C728: =CONCATENATE("PD", TEXT(A728, "1000000")) | D728: 67 | E728: =XLOOKUP(G728, item_category!C:C, item_category!B:B, "Not Found") | F728: OTC Liquids | G728: =XLOOKUP(I728, drug!B:B, drug!A:A, "Not Found") | I728: 1 | J728: =XLOOKUP(L728, uom!C:C, uom!B:B, "Not Found") | K728: Unit(s) | L728: =XLOOKUP(N728, uom!C:C, uom!B:B, "Not Found") | M728: Unit(s) | N728: false | O728: none | P728: =XLOOKUP(R728, classification!C:C, classification!B:B, "Not Found") | Q728: All
A729: 728 | B729: Falbitone Cap | C729: =CONCATENATE("PD", TEXT(A729, "1000000")) | D729: 67 | E729: =XLOOKUP(G729, item_category!C:C, item_category!B:B, "Not Found") | F729: OTC Liquids | G729: =XLOOKUP(I729, drug!B:B, drug!A:A, "Not Found") | H729: Ca | I729: 1 | J729: =XLOOKUP(L729, uom!C:C, uom!B:B, "Not Found") | K729: Unit(s) | L729: =XLOOKUP(N729, uom!C:C, uom!B:B, "Not Found") | M729: Unit(s) | N729: false | O729: none | P729: =XLOOKUP(R729, classification!C:C, classification!B:B, "Not Found") | Q729: All
A730: 729 | B730: Ferbelan Tonic 100ml | C730: =CONCATENATE("PD", TEXT(A730, "1000000")) | D730: 67 | E730: =XLOOKUP(G730, item_category!C:C, item_category!B:B, "Not Found") | F730: OTC Liquids | G730: =XLOOKUP(I730, drug!B:B, drug!A:A, "Not Found") | I730: 1 | J730: =XLOOKUP(L730, uom!C:C, uom!B:B, "Not Found") | K730: Unit(s) | L730: =XLOOKUP(N730, uom!C:C, uom!B:B, "Not Found") | M730: Unit(s) | N730: false | O730: none | P730: =XLOOKUP(R730, classification!C:C, classification!B:B, "Not Found") | Q730: All
A731: 730 | B731: Ferilex Junior Tonic | C731: =CONCATENATE("PD", TEXT(A731, "1000000")) | D731: 67 | E731: =XLOOKUP(G731, item_category!C:C, item_category!B:B, "Not Found") | F731: OTC Liquids | G731: =XLOOKUP(I731, drug!B:B, drug!A:A, "Not Found") | I731: 1 | J731: =XLOOKUP(L731, uom!C:C, uom!B:B, "Not Found") | K731: Unit(s) | L731: =XLOOKUP(N731, uom!C:C, uom!B:B, "Not Found") | M731: Unit(s) | N731: false | O731: none | P731: =XLOOKUP(R731, classification!C:C, classification!B:B, "Not Found") | Q731: All
A732: 731 | B732: Ferilex Tonic B/S | C732: =CONCATENATE("PD", TEXT(A732, "1000000")) | D732: 67 | E732: =XLOOKUP(G732, item_category!C:C, item_category!B:B, "Not Found") | F732: OTC Liquids | G732: =XLOOKUP(I732, drug!B:B, drug!A:A, "Not Found") | I732: 1 | J732: =XLOOKUP(L732, uom!C:C, uom!B:B, "Not Found") | K732: Unit(s) | L732: =XLOOKUP(N732, uom!C:C, uom!B:B, "Not Found") | M732: Unit(s) | N732: false | O732: none | P732: =XLOOKUP(R732, classification!C:C, classification!B:B, "Not Found") | Q732: All
A733: 732 | B733: Ferilex Tonic S/S | C733: =CONCATENATE("PD", TEXT(A733, "1000000")) | D733: 67 | E733: =XLOOKUP(G733, item_category!C:C, item_category!B:B, "Not Found") | F733: OTC Liquids | G733: =XLOOKUP(I733, drug!B:B, drug!A:A, "Not Found") | I733: 1 | J733: =XLOOKUP(L733, uom!C:C, uom!B:B, "Not Found") | K733: Unit(s) | L733: =XLOOKUP(N733, uom!C:C, uom!B:B, "Not Found") | M733: Unit(s) | N733: false | O733: none | P733: =XLOOKUP(R733, classification!C:C, classification!B:B, "Not Found") | Q733: All
A734: 733 | B734: Feriplus Tonic B/S | C734: =CONCATENATE("PD", TEXT(A734, "1000000")) | D734: 67 | E734: =XLOOKUP(G734, item_category!C:C, item_category!B:B, "Not Found") | F734: OTC Liquids | G734: =XLOOKUP(I734, drug!B:B, drug!A:A, "Not Found") | I734: 1 | J734: =XLOOKUP(L734, uom!C:C, uom!B:B, "Not Found") | K734: Unit(s) | L734: =XLOOKUP(N734, uom!C:C, uom!B:B, "Not Found") | M734: Unit(s) | N734: false | O734: none | P734: =XLOOKUP(R734, classification!C:C, classification!B:B, "Not Found") | Q734: All
A735: 734 | B735: Feriplus Tonic M/S | C735: =CONCATENATE("PD", TEXT(A735, "1000000")) | D735: 67 | E735: =XLOOKUP(G735, item_category!C:C, item_category!B:B, "Not Found") | F735: OTC Liquids | G735: =XLOOKUP(I735, drug!B:B, drug!A:A, "Not Found") | I735: 1 | J735: =XLOOKUP(L735, uom!C:C, uom!B:B, "Not Found") | K735: Unit(s) | L735: =XLOOKUP(N735, uom!C:C, uom!B:B, "Not Found") | M735: Unit(s) | N735: false | O735: none | P735: =XLOOKUP(R735, classification!C:C, classification!B:B, "Not Found") | Q735: All
A736: 735 | B736: Feriplus Tonic S/S | C736: =CONCATENATE("PD", TEXT(A736, "1000000")) | D736: 67 | E736: =XLOOKUP(G736, item_category!C:C, item_category!B:B, "Not Found") | F736: OTC Liquids | G736: =XLOOKUP(I736, drug!B:B, drug!A:A, "Not Found") | I736: 1 | J736: =XLOOKUP(L736, uom!C:C, uom!B:B, "Not Found") | K736: Unit(s) | L736: =XLOOKUP(N736, uom!C:C, uom!B:B, "Not Found") | M736: Unit(s) | N736: false | O736: none | P736: =XLOOKUP(R736, classification!C:C, classification!B:B, "Not Found") | Q736: All
A737: 736 | B737: Feritan Plus | C737: =CONCATENATE("PD", TEXT(A737, "1000000")) | D737: 67 | E737: =XLOOKUP(G737, item_category!C:C, item_category!B:B, "Not Found") | F737: OTC Liquids | G737: =XLOOKUP(I737, drug!B:B, drug!A:A, "Not Found") | I737: 1 | J737: =XLOOKUP(L737, uom!C:C, uom!B:B, "Not Found") | K737: Unit(s) | L737: =XLOOKUP(N737, uom!C:C, uom!B:B, "Not Found") | M737: Unit(s) | N737: false | O737: none | P737: =XLOOKUP(R737, classification!C:C, classification!B:B, "Not Found") | Q737: All
A738: 737 | B738: Ferobin Plus Tonic | C738: =CONCATENATE("PD", TEXT(A738, "1000000")) | D738: 67 | E738: =XLOOKUP(G738, item_category!C:C, item_category!B:B, "Not Found") | F738: OTC Liquids | G738: =XLOOKUP(I738, drug!B:B, drug!A:A, "Not Found") | I738: 1 | J738: =XLOOKUP(L738, uom!C:C, uom!B:B, "Not Found") | K738: Unit(s) | L738: =XLOOKUP(N738, uom!C:C, uom!B:B, "Not Found") | M738: Unit(s) | N738: false | O738: none | P738: =XLOOKUP(R738, classification!C:C, classification!B:B, "Not Found") | Q738: All
A739: 738 | B739: Feroglobin Tonic | C739: =CONCATENATE("PD", TEXT(A739, "1000000")) | D739: 67 | E739: =XLOOKUP(G739, item_category!C:C, item_category!B:B, "Not Found") | F739: OTC Liquids | G739: =XLOOKUP(I739, drug!B:B, drug!A:A, "Not Found") | I739: 1 | J739: =XLOOKUP(L739, uom!C:C, uom!B:B, "Not Found") | K739: Unit(s) | L739: =XLOOKUP(N739, uom!C:C, uom!B:B, "Not Found") | M739: Unit(s) | N739: false | O739: none | P739: =XLOOKUP(R739, classification!C:C, classification!B:B, "Not Found") | Q739: All
A740: 739 | B740: Ferotal Blood Tonic 300ml | C740: =CONCATENATE("PD", TEXT(A740, "1000000")) | D740: 67 | E740: =XLOOKUP(G740, item_category!C:C, item_category!B:B, "Not Found") | F740: OTC Liquids | G740: =XLOOKUP(I740, drug!B:B, drug!A:A, "Not Found") | I740: 1 | J740: =XLOOKUP(L740, uom!C:C, uom!B:B, "Not Found") | K740: Unit(s) | L740: =XLOOKUP(N740, uom!C:C, uom!B:B, "Not Found") | M740: Unit(s) | N740: false | O740: none | P740: =XLOOKUP(R740, classification!C:C, classification!B:B, "Not Found") | Q740: All
A741: 740 | B741: Ferotal Extra Tonic 300ml | C741: =CONCATENATE("PD", TEXT(A741, "1000000")) | D741: 67 | E741: =XLOOKUP(G741, item_category!C:C, item_category!B:B, "Not Found") | F741: OTC Liquids | G741: =XLOOKUP(I741, drug!B:B, drug!A:A, "Not Found") | I741: 1 | J741: =XLOOKUP(L741, uom!C:C, uom!B:B, "Not Found") | K741: Unit(s) | L741: =XLOOKUP(N741, uom!C:C, uom!B:B, "Not Found") | M741: Unit(s) | N741: false | O741: none | P741: =XLOOKUP(R741, classification!C:C, classification!B:B, "Not Found") | Q741: All
... A756: 755 | B756: Orheptal Tonic M/S | C756: =CONCATENATE("PD", TEXT(A756, "1000000")) | D756: 67 | E756: =XLOOKUP(G756, item_category!C:C, item_category!B:B, "Not Found") | F756: OTC Liquids | G756: =XLOOKUP(I756, drug!B:B, drug!A:A, "Not Found") | I756: 1 | J756: =XLOOKUP(L756, uom!C:C, uom!B:B, "Not Found") | K756: Unit(s) | L756: =XLOOKUP(N756, uom!C:C, uom!B:B, "Not Found") | M756: Unit(s) | N756: false | O756: none | P756: =XLOOKUP(R756, classification!C:C, classification!B:B, "Not Found") | Q756: All
A757: 756 | B757: Orofer Tonic | C757: =CONCATENATE("PD", TEXT(A757, "1000000")) | D757: 67 | E757: =XLOOKUP(G757, item_category!C:C, item_category!B:B, "Not Found") | F757: OTC Liquids | G757: =XLOOKUP(I757, drug!B:B, drug!A:A, "Not Found") | H757: Orofer | I757: 1 | J757: =XLOOKUP(L757, uom!C:C, uom!B:B, "Not Found") | K757: Unit(s) | L757: =XLOOKUP(N757, uom!C:C, uom!B:B, "Not Found") | M757: Unit(s) | N757: false | O757: none | P757: =XLOOKUP(R757, classification!C:C, classification!B:B, "Not Found") | Q757: All
A758: 757 | B758: Peacetone Tonic BS | C758: =CONCATENATE("PD", TEXT(A758, "1000000")) | D758: 67 | E758: =XLOOKUP(G758, item_category!C:C, item_category!B:B, "Not Found") | F758: OTC Liquids | G758: =XLOOKUP(I758, drug!B:B, drug!A:A, "Not Found") | I758: 1 | J758: =XLOOKUP(L758, uom!C:C, uom!B:B, "Not Found") | K758: Unit(s) | L758: =XLOOKUP(N758, uom!C:C, uom!B:B, "Not Found") | M758: Unit(s) | N758: false | O758: none | P758: =XLOOKUP(R758, classification!C:C, classification!B:B, "Not Found") | Q758: All
A759: 758 | B759: Peacetone Tonic MS | C759: =CONCATENATE("PD", TEXT(A759, "1000000")) | D759: 67 | E759: =XLOOKUP(G759, item_category!C:C, item_category!B:B, "Not Found") | F759: OTC Liquids | G759: =XLOOKUP(I759, drug!B:B, drug!A:A, "Not Found") | I759: 1 | J759: =XLOOKUP(L759, uom!C:C, uom!B:B, "Not Found") | K759: Unit(s) | L759: =XLOOKUP(N759, uom!C:C, uom!B:B, "Not Found") | M759: Unit(s) | N759: false | O759: none | P759: =XLOOKUP(R759, classification!C:C, classification!B:B, "Not Found") | Q759: All
A760: 759 | B760: Peacetone Tonic SS | C760: =CONCATENATE("PD", TEXT(A760, "1000000")) | D760: 67 | E760: =XLOOKUP(G760, item_category!C:C, item_category!B:B, "Not Found") | F760: OTC Liquids | G760: =XLOOKUP(I760, drug!B:B, drug!A:A, "Not Found") | I760: 1 | J760: =XLOOKUP(L760, uom!C:C, uom!B:B, "Not Found") | K760: Unit(s) | L760: =XLOOKUP(N760, uom!C:C, uom!B:B, "Not Found") | M760: Unit(s) | N760: false | O760: none | P760: =XLOOKUP(R760, classification!C:C, classification!B:B, "Not Found") | Q760: All
A761: 760 | B761: Primeron Tonic | C761: =CONCATENATE("PD", TEXT(A761, "1000000")) | D761: 67 | E761: =XLOOKUP(G761, item_category!C:C, item_category!B:B, "Not Found") | F761: OTC Liquids | G761: =XLOOKUP(I761, drug!B:B, drug!A:A, "Not Found") | I761: 1 | J761: =XLOOKUP(L761, uom!C:C, uom!B:B, "Not Found") | K761: Unit(s) | L761: =XLOOKUP(N761, uom!C:C, uom!B:B, "Not Found") | M761: Unit(s) | N761: false | O761: none | P761: =XLOOKUP(R761, classification!C:C, classification!B:B, "Not Found") | Q761: All
A762: 761 | B762: Ranferon Tonic 100ml | C762: =CONCATENATE("PD", TEXT(A762, "1000000")) | D762: 67 | E762: =XLOOKUP(G762, item_category!C:C, item_category!B:B, "Not Found") | F762: OTC Liquids | G762: =XLOOKUP(I762, drug!B:B, drug!A:A, "Not Found") | I762: 1 | J762: =XLOOKUP(L762, uom!C:C, uom!B:B, "Not Found") | K762: Unit(s) | L762: =XLOOKUP(N762, uom!C:C, uom!B:B, "Not Found") | M762: Unit(s) | N762: false | O762: none | P762: =XLOOKUP(R762, classification!C:C, classification!B:B, "Not Found") | Q762: All
A763: 762 | B763: Ranferon Tonic 200ml | C763: =CONCATENATE("PD", TEXT(A763, "1000000")) | D763: 67 | E763: =XLOOKUP(G763, item_category!C:C, item_category!B:B, "Not Found") | F763: OTC Liquids | G763: =XLOOKUP(I763, drug!B:B, drug!A:A, "Not Found") | I763: 1 | J763: =XLOOKUP(L763, uom!C:C, uom!B:B, "Not Found") | K763: Unit(s) | L763: =XLOOKUP(N763, uom!C:C, uom!B:B, "Not Found") | M763: Unit(s) | N763: false | O763: none | P763: =XLOOKUP(R763, classification!C:C, classification!B:B, "Not Found") | Q763: All
A764: 763 | B764: Solotone Tonic | C764: =CONCATENATE("PD", TEXT(A764, "1000000")) | D764: 67 | E764: =XLOOKUP(G764, item_category!C:C, item_category!B:B, "Not Found") | F764: OTC Liquids | G764: =XLOOKUP(I764, drug!B:B, drug!A:A, "Not Found") | I764: 1 | J764: =XLOOKUP(L764, uom!C:C, uom!B:B, "Not Found") | K764: Unit(s) | L764: =XLOOKUP(N764, uom!C:C, uom!B:B, "Not Found") | M764: Unit(s) | N764: false | O764: none | P764: =XLOOKUP(R764, classification!C:C, classification!B:B, "Not Found") | Q764: All
A765: 764 | B765: Super Tonic | C765: =CONCATENATE("PD", TEXT(A765, "1000000")) | D765: 67 | E765: =XLOOKUP(G765, item_category!C:C, item_category!B:B, "Not Found") | F765: OTC Liquids | G765: =XLOOKUP(I765, drug!B:B, drug!A:A, "Not Found") | H765: Super | I765: 1 | J765: =XLOOKUP(L765, uom!C:C, uom!B:B, "Not Found") | K765: Unit(s) | L765: =XLOOKUP(N765, uom!C:C, uom!B:B, "Not Found") | M765: Unit(s) | N765: false | O765: none | P765: =XLOOKUP(R765, classification!C:C, classification!B:B, "Not Found") | Q765: All
A766: 765 | B766: Thiocal 12 Tonic 1 Litre | C766: =CONCATENATE("PD", TEXT(A766, "1000000")) | D766: 67 | E766: =XLOOKUP(G766, item_category!C:C, item_category!B:B, "Not Found") | F766: OTC Liquids | G766: =XLOOKUP(I766, drug!B:B, drug!A:A, "Not Found") | H766: Ca | I766: 1 | J766: =XLOOKUP(L766, uom!C:C, uom!B:B, "Not Found") | K766: Unit(s) | L766: =XLOOKUP(N766, uom!C:C, uom!B:B, "Not Found") | M766: Unit(s) | N766: false | O766: none | P766: =XLOOKUP(R766, classification!C:C, classification!B:B, "Not Found") | Q766: All
A767: 766 | B767: Hollandia Yogurt S/s 315ml | C767: =CONCATENATE("PD", TEXT(A767, "1000000")) | D767: 1 | E767: =XLOOKUP(G767, item_category!C:C, item_category!B:B, "Not Found") | F767: All | G767: =XLOOKUP(I767, drug!B:B, drug!A:A, "Not Found") | I767: 250 | J767: =XLOOKUP(L767, uom!C:C, uom!B:B, "Not Found") | K767: Millilitres | L767: =XLOOKUP(N767, uom!C:C, uom!B:B, "Not Found") | M767: Millilitres | N767: true | O767: lot | P767: =XLOOKUP(R767, classification!C:C, classification!B:B, "Not Found") | Q767: All
A768: 767 | B768: Tonivite Tonic | C768: =CONCATENATE("PD", TEXT(A768, "1000000")) | D768: 67 | E768: =XLOOKUP(G768, item_category!C:C, item_category!B:B, "Not Found") | F768: OTC Liquids | G768: =XLOOKUP(I768, drug!B:B, drug!A:A, "Not Found") | H768: Vit | I768: 1 | J768: =XLOOKUP(L768, uom!C:C, uom!B:B, "Not Found") | K768: Unit(s) | L768: =XLOOKUP(N768, uom!C:C, uom!B:B, "Not Found") | M768: Unit(s) | N768: false | O768: none | P768: =XLOOKUP(R768, classification!C:C, classification!B:B, "Not Found") | Q768: All
A769: 768 | B769: Vamiron Tonic 1Litre | C769: =CONCATENATE("PD", TEXT(A769, "1000000")) | D769: 67 | E769: =XLOOKUP(G769, item_category!C:C, item_category!B:B, "Not Found") | F769: OTC Liquids | G769: =XLOOKUP(I769, drug!B:B, drug!A:A, "Not Found") | H769: Amiro | I769: 1 | J769: =XLOOKUP(L769, uom!C:C, uom!B:B, "Not Found") | K769: Unit(s) | L769: =XLOOKUP(N769, uom!C:C, uom!B:B, "Not Found") | M769: Unit(s) | N769: false | O769: none | P769: =XLOOKUP(R769, classification!C:C, classification!B:B, "Not Found") | Q769: All
A770: 769 | B770: Vamiron Tonic 200mls | C770: =CONCATENATE("PD", TEXT(A770, "1000000")) | D770: 67 | E770: =XLOOKUP(G770, item_category!C:C, item_category!B:B, "Not Found") | F770: OTC Liquids | G770: =XLOOKUP(I770, drug!B:B, drug!A:A, "Not Found") | H770: Amiro | I770: 1 | J770: =XLOOKUP(L770, uom!C:C, uom!B:B, "Not Found") | K770: Unit(s) | L770: =XLOOKUP(N770, uom!C:C, uom!B:B, "Not Found") | M770: Unit(s) | N770: false | O770: none | P770: =XLOOKUP(R770, classification!C:C, classification!B:B, "Not Found") | Q770: All
A771: 770 | B771: Vamis Heamoglobin Tonic 200ml | C771: =CONCATENATE("PD", TEXT(A771, "1000000")) | D771: 67 | E771: =XLOOKUP(G771, item_category!C:C, item_category!B:B, "Not Found") | F771: OTC Liquids | G771: =XLOOKUP(I771, drug!B:B, drug!A:A, "Not Found") | H771: Vamis | I771: 1 | J771: =XLOOKUP(L771, uom!C:C, uom!B:B, "Not Found") | K771: Unit(s) | L771: =XLOOKUP(N771, uom!C:C, uom!B:B, "Not Found") | M771: Unit(s) | N771: false | O771: none | P771: =XLOOKUP(R771, classification!C:C, classification!B:B, "Not Found") | Q771: All
A772: 771 | B772: Vamis Heamoglobin Tonic 300ml | C772: =CONCATENATE("PD", TEXT(A772, "1000000")) | D772: 67 | E772: =XLOOKUP(G772, item_category!C:C, item_category!B:B, "Not Found") | F772: OTC Liquids | G772: =XLOOKUP(I772, drug!B:B, drug!A:A, "Not Found") | H772: Vamis | I772: 1 | J772: =XLOOKUP(L772, uom!C:C, uom!B:B, "Not Found") | K772: Unit(s) | L772: =XLOOKUP(N772, uom!C:C, uom!B:B, "Not Found") | M772: Unit(s) | N772: false | O772: none | P772: =XLOOKUP(R772, classification!C:C, classification!B:B, "Not Found") | Q772: All
A773: 772 | B773: Vamobion Children Blood Tonic 200ml | C773: =CONCATENATE("PD", TEXT(A773, "1000000")) | D773: 67 | E773: =XLOOKUP(G773, item_category!C:C, item_category!B:B, "Not Found") | F773: OTC Liquids | G773: =XLOOKUP(I773, drug!B:B, drug!A:A, "Not Found") | I773: 1 | J773: =XLOOKUP(L773, uom!C:C, uom!B:B, "Not Found") | K773: Unit(s) | L773: =XLOOKUP(N773, uom!C:C, uom!B:B, "Not Found") | M773: Unit(s) | N773: false | O773: none | P773: =XLOOKUP(R773, classification!C:C, classification!B:B, "Not Found") | Q773: All
A774: 773 | B774: King Tonic 200ml | C774: =CONCATENATE("PD", TEXT(A774, "1000000")) | D774: 67 | E774: =XLOOKUP(G774, item_category!C:C, item_category!B:B, "Not Found") | F774: OTC Liquids | G774: =XLOOKUP(I774, drug!B:B, drug!A:A, "Not Found") | I774: 500 | J774: =XLOOKUP(L774, uom!C:C, uom!B:B, "Not Found") | K774: Syrup Bottle | L774: =XLOOKUP(N774, uom!C:C, uom!B:B, "Not Found") | M774: Syrup Bottle | N774: true | O774: lot | P774: =XLOOKUP(R774, classification!C:C, classification!B:B, "Not Found") | Q774: All
A775: 774 | B775: MIM Tonic 100ml | C775: =CONCATENATE("PD", TEXT(A775, "1000000")) | D775: 67 | E775: =XLOOKUP(G775, item_category!C:C, item_category!B:B, "Not Found") | F775: OTC Liquids | G775: =XLOOKUP(I775, drug!B:B, drug!A:A, "Not Found") | I775: 350 | J775: =XLOOKUP(L775, uom!C:C, uom!B:B, "Not Found") | K775: Syrup Bottle | L775: =XLOOKUP(N775, uom!C:C, uom!B:B, "Not Found") | M775: Syrup Bottle | N775: true | O775: lot | P775: =XLOOKUP(R775, classification!C:C, classification!B:B, "Not Found") | Q775: All
A776: 775 | B776: Thiocal 12 Tonic 200ml | C776: =CONCATENATE("PD", TEXT(A776, "1000000")) | D776: 67 | E776: =XLOOKUP(G776, item_category!C:C, item_category!B:B, "Not Found") | F776: OTC Liquids | G776: =XLOOKUP(I776, drug!B:B, drug!A:A, "Not Found") | H776: Ca | I776: 450 | J776: =XLOOKUP(L776, uom!C:C, uom!B:B, "Not Found") | K776: Syrup Bottle | L776: =XLOOKUP(N776, uom!C:C, uom!B:B, "Not Found") | M776: Syrup Bottle | N776: true | O776: lot | P776: =XLOOKUP(R776, classification!C:C, classification!B:B, "Not Found") | Q776: All
A777: 776 | B777: Vamobion Tonic | C777: =CONCATENATE("PD", TEXT(A777, "1000000")) | D777: 67 | E777: =XLOOKUP(G777, item_category!C:C, item_category!B:B, "Not Found") | F777: OTC Liquids | G777: =XLOOKUP(I777, drug!B:B, drug!A:A, "Not Found") | I777: 1 | J777: =XLOOKUP(L777, uom!C:C, uom!B:B, "Not Found") | K777: Unit(s) | L777: =XLOOKUP(N777, uom!C:C, uom!B:B, "Not Found") | M777: Unit(s) | N777: false | O777: none | P777: =XLOOKUP(R777, classification!C:C, classification!B:B, "Not Found") | Q777: All
A778: 777 | B778: Vitaferon Tonic | C778: =CONCATENATE("PD", TEXT(A778, "1000000")) | D778: 67 | E778: =XLOOKUP(G778, item_category!C:C, item_category!B:B, "Not Found") | F778: OTC Liquids | G778: =XLOOKUP(I778, drug!B:B, drug!A:A, "Not Found") | H778: Vit | I778: 1 | J778: =XLOOKUP(L778, uom!C:C, uom!B:B, "Not Found") | K778: Unit(s) | L778: =XLOOKUP(N778, uom!C:C, uom!B:B, "Not Found") | M778: Unit(s) | N778: false | O778: none | P778: =XLOOKUP(R778, classification!C:C, classification!B:B, "Not Found") | Q778: All
...

Sheet drug
A1: code | B1: name | C1: genericClass | D1: pharmaceuticalClass | E1: generalUse | F1: adultDosage | G1: pediatricDosage | H1: appendixDosages | I1: pharmaceuticsCode | J1: drugComponentNames | K1: pharmaceuticsNames | L1: pharmaceuticsDrugClasses | M1: drugComponents | N1: uuid | O1: sync_status | P1: sync_message | Q1: sync_time
A2: GN-00001 | B2: Abacavir | C2: Anti-Infective Medicines | D2: Nucleoside + nucleotide reverse transcriptase inhibitors | E2: Listed in the Nigeria Essential Medicines List (NDF/EDL) for condition-specific treatment. | F2: Use strength- and indication-specific dosing as provided in the Nigeria Drug Formulary. | G2: Use age/weight-based dosing according to the Nigeria Drug Formulary and pediatric guidance. | I2: =XLOOKUP(K2, pharmaceutical_index!B:B, pharmaceutical_index!A:A, "Not Found") | J2: Abacavir | K2: Abacavir | L2: Nucleoside + nucleotide reverse transcriptase inhibitors | M2: Abacavir
A3: GN-00002 | B3: Abacavir + Efavirenz + Lamivudine | C3: Unclassified | D3: General | E3: Listed in the Nigeria Essential Medicines List (NDF/EDL) for condition-specific treatment. | F3: Use strength- and indication-specific dosing as provided in the Nigeria Drug Formulary. | G3: Use age/weight-based dosing according to the Nigeria Drug Formulary and pediatric guidance. | I3: =XLOOKUP(K3, pharmaceutical_index!B:B, pharmaceutical_index!A:A, "Not Found") | J3: Abacavir,Efavirenz,Lamivudine | K3: Abacavir + Efavirenz + Lamivudine | L3: General | M3: Abacavir, Efavirenz, Lamivudine
A4: GN-00003 | B4: Abacavir + Lamivudine | C4: Anti-Infective Medicines | D4: Fixed-dose combinations (adult First line) | E4: Listed in the Nigeria Essential Medicines List (NDF/EDL) for condition-specific treatment. | F4: Use strength- and indication-specific dosing as provided in the Nigeria Drug Formulary. | G4: Use age/weight-based dosing according to the Nigeria Drug Formulary and pediatric guidance. | I4: =XLOOKUP(K4, pharmaceutical_index!B:B, pharmaceutical_index!A:A, "Not Found") | J4: Abacavir,Lamivudine | K4: Abacavir + Lamivudine | L4: Fixed-dose combinations (adult First line) | M4: Abacavir, Lamivudine
A5: GN-00004 | B5: Abiraterone | C5: Antineoplastic, Immunosuppressive Medicines And Adjuvants | D5: General | E5: Listed in the Nigeria Essential Medicines List (NDF/EDL) for condition-specific treatment. | F5: Use strength- and indication-specific dosing as provided in the Nigeria Drug Formulary. | G5: Use age/weight-based dosing according to the Nigeria Drug Formulary and pediatric guidance. | I5: =XLOOKUP(K5, pharmaceutical_index!B:B, pharmaceutical_index!A:A, "Not Found") | J5: Abiraterone | K5: Abiraterone | L5: General | M5: Abiraterone
A6: GN-00005 | B6: Acetic acid | C6: Medicines For Ear, Nose And Throat | D6: General | E6: Listed in the Nigeria Essential Medicines List (NDF/EDL) for condition-specific treatment. | F6: Use strength- and indication-specific dosing as provided in the Nigeria Drug Formulary. | G6: Use age/weight-based dosing according to the Nigeria Drug Formulary and pediatric guidance. | I6: =XLOOKUP(K6, pharmaceutical_index!B:B, pharmaceutical_index!A:A, "Not Found") | J6: Acetic acid | K6: Acetic acid | L6: General | M6: Acetic acid
A7: GN-00006 | B7: Acetylcysteine | C7: Antidotes And Other Substances Used In Poisonings | D7: Specific | E7: Listed in the Nigeria Essential Medicines List (NDF/EDL) for condition-specific treatment. | F7: Use strength- and indication-specific dosing as provided in the Nigeria Drug Formulary. | G7: Use age/weight-based dosing according to the Nigeria Drug Formulary and pediatric guidance. | I7: =XLOOKUP(K7, pharmaceutical_index!B:B, pharmaceutical_index!A:A, "Not Found") | J7: Acetylcysteine | K7: Acetylcysteine | L7: Specific | M7: Acetylcysteine
A8: GN-00007 | B8: Acetylsalicylic acid | C8: Cardiovascular Medicines | D8: Anti-platelet medicines | E8: Listed in the Nigeria Essential Medicines List (NDF/EDL) for condition-specific treatment. | F8: Use strength- and indication-specific dosing as provided in the Nigeria Drug Formulary. | G8: Use age/weight-based dosing according to the Nigeria Drug Formulary and pediatric guidance. | I8: =XLOOKUP(K8, pharmaceutical_index!B:B, pharmaceutical_index!A:A, "Not Found") | J8: Acetylsalicylic acid | K8: Acetylsalicylic acid | L8: Anti-platelet medicines | M8: Acetylsalicylic acid
A9: GN-00008 | B9: Aciclovir | C9: Anti-Infective Medicines | D9: Antiherpes medicines | E9: Listed in the Nigeria Essential Medicines List (NDF/EDL) for condition-specific treatment. | F9: Use strength- and indication-specific dosing as provided in the Nigeria Drug Formulary. | G9: Use age/weight-based dosing according to the Nigeria Drug Formulary and pediatric guidance. | I9: =XLOOKUP(K9, pharmaceutical_index!B:B, pharmaceutical_index!A:A, "Not Found") | J9: Aciclovir | K9: Aciclovir | L9: Antiherpes medicines | M9: Aciclovir
A10: GN-00009 | B10: Actinomycin-D | C10: Antineoplastic, Immunosuppressive Medicines And Adjuvants | D10: General | E10: Listed in the Nigeria Essential Medicines List (NDF/EDL) for condition-specific treatment. | F10: Use strength- and indication-specific dosing as provided in the Nigeria Drug Formulary. | G10: Use age/weight-based dosing according to the Nigeria Drug Formulary and pediatric guidance. | I10: =XLOOKUP(K10, pharmaceutical_index!B:B, pharmaceutical_index!A:A, "Not Found") | J10: Actinomycin-D | K10: Actinomycin-D | L10: General | M10: Actinomycin-D
A11: GN-00010 | B11: Adalimumab | C11: Antineoplastic, Immunosuppressive Medicines And Adjuvants | D11: General | E11: Listed in the Nigeria Essential Medicines List (NDF/EDL) for condition-specific treatment. | F11: Use strength- and indication-specific dosing as provided in the Nigeria Drug Formulary. | G11: Use age/weight-based dosing according to the Nigeria Drug Formulary and pediatric guidance. | I11: =XLOOKUP(K11, pharmaceutical_index!B:B, pharmaceutical_index!A:A, "Not Found") | J11: Adalimumab | K11: Adalimumab | L11: General | M11: Adalimumab
A12: GN-00011 | B12: Albendazole | C12: Anti-Infective Medicines | D12: Antifilarials | E12: Listed in the Nigeria Essential Medicines List (NDF/EDL) for condition-specific treatment. | F12: Use strength- and indication-specific dosing as provided in the Nigeria Drug Formulary. | G12: Use age/weight-based dosing according to the Nigeria Drug Formulary and pediatric guidance. | I12: =XLOOKUP(K12, pharmaceutical_index!B:B, pharmaceutical_index!A:A, "Not Found") | J12: Albendazole | K12: Albendazole | L12: Antifilarials | M12: Albendazole
A13: GN-00012 | B13: Alfuzosin | C13: Urinary And Erectile Dysfunctions Medicines | D13: General | E13: Listed in the Nigeria Essential Medicines List (NDF/EDL) for condition-specific treatment. | F13: Use strength- and indication-specific dosing as provided in the Nigeria Drug Formulary. | G13: Use age/weight-based dosing according to the Nigeria Drug Formulary and pediatric guidance. | I13: =XLOOKUP(K13, pharmaceutical_index!B:B, pharmaceutical_index!A:A, "Not Found") | J13: Alfuzosin | K13: Alfuzosin | L13: General | M13: Alfuzosin
... A62: GN-00061 | B62: Bicalutamide | C62: Antineoplastic, Immunosuppressive Medicines And Adjuvants | D62: General | E62: Listed in the Nigeria Essential Medicines List (NDF/EDL) for condition-specific treatment. | F62: Use strength- and indication-specific dosing as provided in the Nigeria Drug Formulary. | G62: Use age/weight-based dosing according to the Nigeria Drug Formulary and pediatric guidance. | I62: =XLOOKUP(K62, pharmaceutical_index!B:B, pharmaceutical_index!A:A, "Not Found") | J62: Bicalutamide | K62: Bicalutamide | L62: General | M62: Bicalutamide
A63: GN-00062 | B63: Biotin | C63: Vitamins, Minerals And Nutritionals | D63: General | E63: Listed in the Nigeria Essential Medicines List (NDF/EDL) for condition-specific treatment. | F63: Use strength- and indication-specific dosing as provided in the Nigeria Drug Formulary. | G63: Use age/weight-based dosing according to the Nigeria Drug Formulary and pediatric guidance. | H63: [object Object],[object Object] | I63: =XLOOKUP(K63, pharmaceutical_index!B:B, pharmaceutical_index!A:A, "Not Found") | J63: Biotin | K63: Biotin | L63: General | M63: Biotin
A64: GN-00063 | B64: Biperiden | C64: Medicines For Mental And Behavioural Disorders | D64: Antidotes to antipsychotic medicines | E64: Listed in the Nigeria Essential Medicines List (NDF/EDL) for condition-specific treatment. | F64: Use strength- and indication-specific dosing as provided in the Nigeria Drug Formulary. | G64: Use age/weight-based dosing according to the Nigeria Drug Formulary and pediatric guidance. | I64: =XLOOKUP(K64, pharmaceutical_index!B:B, pharmaceutical_index!A:A, "Not Found") | J64: Biperiden | K64: Biperiden | L64: Antidotes to antipsychotic medicines | M64: Biperiden
A65: GN-00064 | B65: Biphasic isophane insulin | C65: Hormones, Other Endocrine Medicines And Contraceptives | D65: Insulin preparations | E65: Listed in the Nigeria Essential Medicines List (NDF/EDL) for condition-specific treatment. | F65: Use strength- and indication-specific dosing as provided in the Nigeria Drug Formulary. | G65: Use age/weight-based dosing according to the Nigeria Drug Formulary and pediatric guidance. | I65: =XLOOKUP(K65, pharmaceutical_index!B:B, pharmaceutical_index!A:A, "Not Found") | J65: Biphasic isophane insulin | K65: Biphasic isophane insulin | L65: Insulin preparations | M65: Biphasic isophane insulin
A66: GN-00065 | B66: Bleomycin | C66: Antineoplastic, Immunosuppressive Medicines And Adjuvants | D66: General | E66: Listed in the Nigeria Essential Medicines List (NDF/EDL) for condition-specific treatment. | F66: Use strength- and indication-specific dosing as provided in the Nigeria Drug Formulary. | G66: Use age/weight-based dosing according to the Nigeria Drug Formulary and pediatric guidance. | I66: =XLOOKUP(K66, pharmaceutical_index!B:B, pharmaceutical_index!A:A, "Not Found") | J66: Bleomycin | K66: Bleomycin | L66: General | M66: Bleomycin
A67: GN-00066 | B67: Bortezomib | C67: Antineoplastic, Immunosuppressive Medicines And Adjuvants | D67: General | E67: Listed in the Nigeria Essential Medicines List (NDF/EDL) for condition-specific treatment. | F67: Use strength- and indication-specific dosing as provided in the Nigeria Drug Formulary. | G67: Use age/weight-based dosing according to the Nigeria Drug Formulary and pediatric guidance. | I67: =XLOOKUP(K67, pharmaceutical_index!B:B, pharmaceutical_index!A:A, "Not Found") | J67: Bortezomib | K67: Bortezomib | L67: General | M67: Bortezomib
A68: GN-00067 | B68: Bromazepam | C68: Medicines For Mental And Behavioural Disorders | D68: Medicines for anxiety disorders | E68: Listed in the Nigeria Essential Medicines List (NDF/EDL) for condition-specific treatment. | F68: Use strength- and indication-specific dosing as provided in the Nigeria Drug Formulary. | G68: Use age/weight-based dosing according to the Nigeria Drug Formulary and pediatric guidance. | I68: =XLOOKUP(K68, pharmaceutical_index!B:B, pharmaceutical_index!A:A, "Not Found") | J68: Bromazepam | K68: Bromazepam | L68: Medicines for anxiety disorders | M68: Bromazepam
A69: GN-00068 | B69: Budesonide | C69: Medicines Acting On The Respiratory Tract | D69: Antiasthmatic medicines | E69: Listed in the Nigeria Essential Medicines List (NDF/EDL) for condition-specific treatment. | F69: Use strength- and indication-specific dosing as provided in the Nigeria Drug Formulary. | G69: Use age/weight-based dosing according to the Nigeria Drug Formulary and pediatric guidance. | I69: =XLOOKUP(K69, pharmaceutical_index!B:B, pharmaceutical_index!A:A, "Not Found") | J69: Budesonide | K69: Budesonide | L69: Antiasthmatic medicines | M69: Budesonide
A70: GN-00069 | B70: Bupivacaine | C70: Anaesthetics, Preoperative Medicines And Medical Gases | D70: Local anaesthetics | E70: Listed in the Nigeria Essential Medicines List (NDF/EDL) for condition-specific treatment. | F70: Use strength- and indication-specific dosing as provided in the Nigeria Drug Formulary. | G70: Use age/weight-based dosing according to the Nigeria Drug Formulary and pediatric guidance. | I70: =XLOOKUP(K70, pharmaceutical_index!B:B, pharmaceutical_index!A:A, "Not Found") | J70: Bupivacaine | K70: Bupivacaine | L70: Local anaesthetics | M70: Bupivacaine
A71: GN-00070 | B71: Buprenorphine | C71: Medicines For Mental And Behavioural Disorders | D71: Medicines used in substance dependence programmes (See Restricted Medicines List) | E71: Listed in the Nigeria Essential Medicines List (NDF/EDL) for condition-specific treatment. | F71: Use strength- and indication-specific dosing as provided in the Nigeria Drug Formulary. | G71: Use age/weight-based dosing according to the Nigeria Drug Formulary and pediatric guidance. | I71: =XLOOKUP(K71, pharmaceutical_index!B:B, pharmaceutical_index!A:A, "Not Found") | J71: Buprenorphine | K71: Buprenorphine | L71: Medicines used in substance dependence programmes (See Restricted Medicines List) | M71: Buprenorphine
A72: GN-00071 | B72: Buserelin | C72: Antineoplastic, Immunosuppressive Medicines And Adjuvants | D72: General | E72: Listed in the Nigeria Essential Medicines List (NDF/EDL) for condition-specific treatment. | F72: Use strength- and indication-specific dosing as provided in the Nigeria Drug Formulary. | G72: Use age/weight-based dosing according to the Nigeria Drug Formulary and pediatric guidance. | I72: =XLOOKUP(K72, pharmaceutical_index!B:B, pharmaceutical_index!A:A, "Not Found") | J72: Buserelin | K72: Buserelin | L72: General | M72: Buserelin
A73: GN-00072 | B73: Busulfan (Busulphan) | C73: Antineoplastic, Immunosuppressive Medicines And Adjuvants | D73: General | E73: Listed in the Nigeria Essential Medicines List (NDF/EDL) for condition-specific treatment. | F73: Use strength- and indication-specific dosing as provided in the Nigeria Drug Formulary. | G73: Use age/weight-based dosing according to the Nigeria Drug Formulary and pediatric guidance. | I73: =XLOOKUP(K73, pharmaceutical_index!B:B, pharmaceutical_index!A:A, "Not Found") | J73: Busulfan | K73: Busulfan (Busulphan) | L73: General | M73: Busulfan
A74: GN-00073 | B74: Calamine | C74: Unclassified | D74: General | E74: Listed in the Nigeria Essential Medicines List (NDF/EDL) for condition-specific treatment. | F74: Use strength- and indication-specific dosing as provided in the Nigeria Drug Formulary. | G74: Use age/weight-based dosing according to the Nigeria Drug Formulary and pediatric guidance. | I74: =XLOOKUP(K74, pharmaceutical_index!B:B, pharmaceutical_index!A:A, "Not Found") | J74: Calamine | K74: Calamine | L74: General | M74: Calamine
A75: GN-00074 | B75: Calamine + Zinc oxide | C75: Dermatologicals | D75: General | E75: Listed in the Nigeria Essential Medicines List (NDF/EDL) for condition-specific treatment. | F75: Use strength- and indication-specific dosing as provided in the Nigeria Drug Formulary. | G75: Use age/weight-based dosing according to the Nigeria Drug Formulary and pediatric guidance. | I75: =XLOOKUP(K75, pharmaceutical_index!B:B, pharmaceutical_index!A:A, "Not Found") | J75: Calamine,Zinc oxide | K75: Calamine + Zinc oxide | L75: General | M75: Calamine, Zinc oxide
... A209: GN-00208 | B209: Fluticasone furoate | C209: Medicines For Ear, Nose And Throat | D209: General | E209: Listed in the Nigeria Essential Medicines List (NDF/EDL) for condition-specific treatment. | F209: Use strength- and indication-specific dosing as provided in the Nigeria Drug Formulary. | G209: Use age/weight-based dosing according to the Nigeria Drug Formulary and pediatric guidance. | I209: =XLOOKUP(K209, pharmaceutical_index!B:B, pharmaceutical_index!A:A, "Not Found") | J209: Fluticasone furoate | K209: Fluticasone furoate | L209: General | M209: Fluticasone furoate
A210: GN-00209 | B210: Folic acid | C210: Medicines Affecting The Blood | D210: Antianaemia medicines (Haematinics) | E210: Listed in the Nigeria Essential Medicines List (NDF/EDL) for condition-specific treatment. | F210: Use strength- and indication-specific dosing as provided in the Nigeria Drug Formulary. | G210: Use age/weight-based dosing according to the Nigeria Drug Formulary and pediatric guidance. | H210: [object Object],[object Object],[object Object],[object Object] | I210: =XLOOKUP(K210, pharmaceutical_index!B:B, pharmaceutical_index!A:A, "Not Found") | J210: Folic acid | K210: Folic acid | L210: Antianaemia medicines (Haematinics) | M210: Folic acid
A211: GN-00210 | B211: Fomepizole | C211: Antidotes And Other Substances Used In Poisonings | D211: Specific | E211: Listed in the Nigeria Essential Medicines List (NDF/EDL) for condition-specific treatment. | F211: Use strength- and indication-specific dosing as provided in the Nigeria Drug Formulary. | G211: Use age/weight-based dosing according to the Nigeria Drug Formulary and pediatric guidance. | I211: =XLOOKUP(K211, pharmaceutical_index!B:B, pharmaceutical_index!A:A, "Not Found") | J211: Fomepizole | K211: Fomepizole | L211: Specific | M211: Fomepizole
A212: GN-00211 | B212: Formaldehyde | C212: Antiseptics And Disinfectants | D212: General | E212: Listed in the Nigeria Essential Medicines List (NDF/EDL) for condition-specific treatment. | F212: Use strength- and indication-specific dosing as provided in the Nigeria Drug Formulary. | G212: Use age/weight-based dosing according to the Nigeria Drug Formulary and pediatric guidance. | I212: =XLOOKUP(K212, pharmaceutical_index!B:B, pharmaceutical_index!A:A, "Not Found") | J212: Formaldehyde | K212: Formaldehyde | L212: General | M212: Formaldehyde
A213: GN-00212 | B213: Furosemide | C213: Cardiovascular Medicines | D213: Medicines used in heart failure | E213: Listed in the Nigeria Essential Medicines List (NDF/EDL) for condition-specific treatment. | F213: Use strength- and indication-specific dosing as provided in the Nigeria Drug Formulary. | G213: Use age/weight-based dosing according to the Nigeria Drug Formulary and pediatric guidance. | I213: =XLOOKUP(K213, pharmaceutical_index!B:B, pharmaceutical_index!A:A, "Not Found") | J213: Furosemide | K213: Furosemide | L213: Medicines used in heart failure | M213: Furosemide
A214: GN-00213 | B214: Gatifloxacin | C214: Anti-Infective Medicines | D214: Anti-tuberculosis medicines | E214: Listed in the Nigeria Essential Medicines List (NDF/EDL) for condition-specific treatment. | F214: Use strength- and indication-specific dosing as provided in the Nigeria Drug Formulary. | G214: Use age/weight-based dosing according to the Nigeria Drug Formulary and pediatric guidance. | I214: =XLOOKUP(K214, pharmaceutical_index!B:B, pharmaceutical_index!A:A, "Not Found") | J214: Gatifloxacin | K214: Gatifloxacin | L214: Anti-tuberculosis medicines | M214: Gatifloxacin
A215: GN-00214 | B215: Gemcitabine | C215: Antineoplastic, Immunosuppressive Medicines And Adjuvants | D215: General | E215: Listed in the Nigeria Essential Medicines List (NDF/EDL) for condition-specific treatment. | F215: Use strength- and indication-specific dosing as provided in the Nigeria Drug Formulary. | G215: Use age/weight-based dosing according to the Nigeria Drug Formulary and pediatric guidance. | I215: =XLOOKUP(K215, pharmaceutical_index!B:B, pharmaceutical_index!A:A, "Not Found") | J215: Gemcitabine | K215: Gemcitabine | L215: General | M215: Gemcitabine
A216: GN-00215 | B216: Gentamicin | C216: Anti-Infective Medicines | D216: Antibacterial medicines | E216: Listed in the Nigeria Essential Medicines List (NDF/EDL) for condition-specific treatment. | F216: Use strength- and indication-specific dosing as provided in the Nigeria Drug Formulary. | G216: Use age/weight-based dosing according to the Nigeria Drug Formulary and pediatric guidance. | I216: =XLOOKUP(K216, pharmaceutical_index!B:B, pharmaceutical_index!A:A, "Not Found") | J216: Gentamicin | K216: Gentamicin | L216: Antibacterial medicines | M216: Gentamicin
A217: GN-00216 | B217: Gentian violet | C217: Dermatological Medicines | D217: Anti-infective medicines | E217: Listed in the Nigeria Essential Medicines List (NDF/EDL) for condition-specific treatment. | F217: Use strength- and indication-specific dosing as provided in the Nigeria Drug Formulary. | G217: Use age/weight-based dosing according to the Nigeria Drug Formulary and pediatric guidance. | I217: =XLOOKUP(K217, pharmaceutical_index!B:B, pharmaceutical_index!A:A, "Not Found") | J217: Gentian violet | K217: Gentian violet | L217: Anti-infective medicines | M217: Gentian violet
A218: GN-00217 | B218: Glibenclamide | C218: Hormones, Other Endocrine Medicines And Contraceptives | D218: Oral antidiabetic medicines | E218: Listed in the Nigeria Essential Medicines List (NDF/EDL) for condition-specific treatment. | F218: Use strength- and indication-specific dosing as provided in the Nigeria Drug Formulary. | G218: Use age/weight-based dosing according to the Nigeria Drug Formulary and pediatric guidance. | I218: =XLOOKUP(K218, pharmaceutical_index!B:B, pharmaceutical_index!A:A, "Not Found") | J218: Glibenclamide | K218: Glibenclamide | L218: Oral antidiabetic medicines | M218: Glibenclamide
A219: GN-00218 | B219: Gliclazide | C219: Hormones, Other Endocrine Medicines And Contraceptives | D219: Oral antidiabetic medicines | E219: Listed in the Nigeria Essential Medicines List (NDF/EDL) for condition-specific treatment. | F219: Use strength- and indication-specific dosing as provided in the Nigeria Drug Formulary. | G219: Use age/weight-based dosing according to the Nigeria Drug Formulary and pediatric guidance. | I219: =XLOOKUP(K219, pharmaceutical_index!B:B, pharmaceutical_index!A:A, "Not Found") | J219: Gliclazide | K219: Gliclazide | L219: Oral antidiabetic medicines | M219: Gliclazide
A220: GN-00219 | B220: Glimepyride | C220: Unclassified | D220: General | E220: Listed in the Nigeria Essential Medicines List (NDF/EDL) for condition-specific treatment. | F220: Use strength- and indication-specific dosing as provided in the Nigeria Drug Formulary. | G220: Use age/weight-based dosing according to the Nigeria Drug Formulary and pediatric guidance. | I220: =XLOOKUP(K220, pharmaceutical_index!B:B, pharmaceutical_index!A:A, "Not Found") | J220: Glimepyride | K220: Glimepyride | L220: General | M220: Glimepyride
A221: GN-00220 | B221: Glucagon | C221: Hormones, Other Endocrine Medicines And Contraceptives | D221: Medicines for hypoglycaemia | E221: Listed in the Nigeria Essential Medicines List (NDF/EDL) for condition-specific treatment. | F221: Use strength- and indication-specific dosing as provided in the Nigeria Drug Formulary. | G221: Use age/weight-based dosing according to the Nigeria Drug Formulary and pediatric guidance. | I221: =XLOOKUP(K221, pharmaceutical_index!B:B, pharmaceutical_index!A:A, "Not Found") | J221: Glucagon | K221: Glucagon | L221: Medicines for hypoglycaemia | M221: Glucagon
A222: GN-00221 | B222: Glucose | C222: Gastrointestinal Medicines | D222: Oral rehydration | E222: Listed in the Nigeria Essential Medicines List (NDF/EDL) for condition-specific treatment. | F222: Use strength- and indication-specific dosing as provided in the Nigeria Drug Formulary. | G222: Use age/weight-based dosing according to the Nigeria Drug Formulary and pediatric guidance. | I222: =XLOOKUP(K222, pharmaceutical_index!B:B, pharmaceutical_index!A:A, "Not Found") | J222: Glucose | K222: Glucose | L222: Oral rehydration | M222: Glucose
... A351: GN-00350 | B351: Neostigmine | C351: Anaesthetics, Preoperative Medicines And Medical Gases | D351: Skeletal muscle relaxants and cholinesterase inhibitors | E351: Listed in the Nigeria Essential Medicines List (NDF/EDL) for condition-specific treatment. | F351: Use strength- and indication-specific dosing as provided in the Nigeria Drug Formulary. | G351: Use age/weight-based dosing according to the Nigeria Drug Formulary and pediatric guidance. | I351: =XLOOKUP(K351, pharmaceutical_index!B:B, pharmaceutical_index!A:A, "Not Found") | J351: Neostigmine | K351: Neostigmine | L351: Skeletal muscle relaxants and cholinesterase inhibitors | M351: Neostigmine
A352: GN-00351 | B352: Nicotinamide | C352: Vitamins, Minerals And Nutritionals | D352: General | E352: Listed in the Nigeria Essential Medicines List (NDF/EDL) for condition-specific treatment. | F352: Use strength- and indication-specific dosing as provided in the Nigeria Drug Formulary. | G352: Use age/weight-based dosing according to the Nigeria Drug Formulary and pediatric guidance. | H352: [object Object],[object Object],[object Object],[object Object] | I352: =XLOOKUP(K352, pharmaceutical_index!B:B, pharmaceutical_index!A:A, "Not Found") | J352: Nicotinamide | K352: Nicotinamide | L352: General | M352: Nicotinamide
A353: GN-00352 | B353: Nifedipine | C353: Cardiovascular Medicines | D353: Antihypertensive medicines | E353: Listed in the Nigeria Essential Medicines List (NDF/EDL) for condition-specific treatment. | F353: Use strength- and indication-specific dosing as provided in the Nigeria Drug Formulary. | G353: Use age/weight-based dosing according to the Nigeria Drug Formulary and pediatric guidance. | I353: =XLOOKUP(K353, pharmaceutical_index!B:B, pharmaceutical_index!A:A, "Not Found") | J353: Nifedipine | K353: Nifedipine | L353: Antihypertensive medicines | M353: Nifedipine
A354: GN-00353 | B354: Nifurtimox | C354: Anti-Infective Medicines | D354: Medicines for the treatment of second stage African trypanosomiasis | E354: Listed in the Nigeria Essential Medicines List (NDF/EDL) for condition-specific treatment. | F354: Use strength- and indication-specific dosing as provided in the Nigeria Drug Formulary. | G354: Use age/weight-based dosing according to the Nigeria Drug Formulary and pediatric guidance. | I354: =XLOOKUP(K354, pharmaceutical_index!B:B, pharmaceutical_index!A:A, "Not Found") | J354: Nifurtimox | K354: Nifurtimox | L354: Medicines for the treatment of second stage African trypanosomiasis | M354: Nifurtimox
A355: GN-00354 | B355: Nimodipine | C355: Cardiovascular Medicines | D355: Antihypertensive medicines | E355: Listed in the Nigeria Essential Medicines List (NDF/EDL) for condition-specific treatment. | F355: Use strength- and indication-specific dosing as provided in the Nigeria Drug Formulary. | G355: Use age/weight-based dosing according to the Nigeria Drug Formulary and pediatric guidance. | I355: =XLOOKUP(K355, pharmaceutical_index!B:B, pharmaceutical_index!A:A, "Not Found") | J355: Nimodipine | K355: Nimodipine | L355: Antihypertensive medicines | M355: Nimodipine
A356: GN-00355 | B356: Nitrofurantoin | C356: Anti-Infective Medicines | D356: Antibacterial medicines | E356: Listed in the Nigeria Essential Medicines List (NDF/EDL) for condition-specific treatment. | F356: Use strength- and indication-specific dosing as provided in the Nigeria Drug Formulary. | G356: Use age/weight-based dosing according to the Nigeria Drug Formulary and pediatric guidance. | I356: =XLOOKUP(K356, pharmaceutical_index!B:B, pharmaceutical_index!A:A, "Not Found") | J356: Nitrofurantoin | K356: Nitrofurantoin | L356: Antibacterial medicines | M356: Nitrofurantoin
A357: GN-00356 | B357: Nitrous oxide | C357: Anaesthetics, Preoperative Medicines And Medical Gases | D357: Inhalational medicines | E357: Listed in the Nigeria Essential Medicines List (NDF/EDL) for condition-specific treatment. | F357: Use strength- and indication-specific dosing as provided in the Nigeria Drug Formulary. | G357: Use age/weight-based dosing according to the Nigeria Drug Formulary and pediatric guidance. | I357: =XLOOKUP(K357, pharmaceutical_index!B:B, pharmaceutical_index!A:A, "Not Found") | J357: Nitrous oxide | K357: Nitrous oxide | L357: Inhalational medicines | M357: Nitrous oxide
A358: GN-00357 | B358: Nystatin | C358: Anti-Infective Medicines | D358: Antifungal medicines (systemic) | E358: Listed in the Nigeria Essential Medicines List (NDF/EDL) for condition-specific treatment. | F358: Use strength- and indication-specific dosing as provided in the Nigeria Drug Formulary. | G358: Use age/weight-based dosing according to the Nigeria Drug Formulary and pediatric guidance. | I358: =XLOOKUP(K358, pharmaceutical_index!B:B, pharmaceutical_index!A:A, "Not Found") | J358: Nystatin | K358: Nystatin | L358: Antifungal medicines (systemic) | M358: Nystatin
A359: GN-00358 | B359: Octreotide | C359: Hormones, Other Endocrine Medicines And Contraceptives | D359: Other hormone inhibitor | E359: Listed in the Nigeria Essential Medicines List (NDF/EDL) for condition-specific treatment. | F359: Use strength- and indication-specific dosing as provided in the Nigeria Drug Formulary. | G359: Use age/weight-based dosing according to the Nigeria Drug Formulary and pediatric guidance. | I359: =XLOOKUP(K359, pharmaceutical_index!B:B, pharmaceutical_index!A:A, "Not Found") | J359: Octreotide | K359: Octreotide | L359: Other hormone inhibitor | M359: Octreotide
A360: GN-00359 | B360: Olopatadine | C360: Ophthalmological Preparations | D360: Anti-inflammatory and anti-allergic medicines | E360: Listed in the Nigeria Essential Medicines List (NDF/EDL) for condition-specific treatment. | F360: Use strength- and indication-specific dosing as provided in the Nigeria Drug Formulary. | G360: Use age/weight-based dosing according to the Nigeria Drug Formulary and pediatric guidance. | I360: =XLOOKUP(K360, pharmaceutical_index!B:B, pharmaceutical_index!A:A, "Not Found") | J360: Olopatadine | K360: Olopatadine | L360: Anti-inflammatory and anti-allergic medicines | M360: Olopatadine
A361: GN-00360 | B361: Omeprazole | C361: Gastrointestinal Medicines | D361: Antiulcer medicines | E361: Listed in the Nigeria Essential Medicines List (NDF/EDL) for condition-specific treatment. | F361: Use strength- and indication-specific dosing as provided in the Nigeria Drug Formulary. | G361: Use age/weight-based dosing according to the Nigeria Drug Formulary and pediatric guidance. | I361: =XLOOKUP(K361, pharmaceutical_index!B:B, pharmaceutical_index!A:A, "Not Found") | J361: Omeprazole | K361: Omeprazole | L361: Antiulcer medicines | M361: Omeprazole
A362: GN-00361 | B362: Ondansetron | C362: Antineoplastic, Immunosuppressive Medicines And Adjuvants | D362: General | E362: Listed in the Nigeria Essential Medicines List (NDF/EDL) for condition-specific treatment. | F362: Use strength- and indication-specific dosing as provided in the Nigeria Drug Formulary. | G362: Use age/weight-based dosing according to the Nigeria Drug Formulary and pediatric guidance. | I362: =XLOOKUP(K362, pharmaceutical_index!B:B, pharmaceutical_index!A:A, "Not Found") | J362: Ondansetron | K362: Ondansetron | L362: General | M362: Ondansetron
A363: GN-00362 | B363: Oxamniquine | C363: Anti-Infective Medicines | D363: Intestinal anthelminthics | E363: Listed in the Nigeria Essential Medicines List (NDF/EDL) for condition-specific treatment. | F363: Use strength- and indication-specific dosing as provided in the Nigeria Drug Formulary. | G363: Use age/weight-based dosing according to the Nigeria Drug Formulary and pediatric guidance. | I363: =XLOOKUP(K363, pharmaceutical_index!B:B, pharmaceutical_index!A:A, "Not Found") | J363: Oxamniquine | K363: Oxamniquine | L363: Intestinal anthelminthics | M363: Oxamniquine
A364: GN-00363 | B364: Oxycodone | C364: Medicines For Mental And Behavioural Disorders | D364: Medicines used in substance dependence programmes | E364: Listed in the Nigeria Essential Medicines List (NDF/EDL) for condition-specific treatment. | F364: Use strength- and indication-specific dosing as provided in the Nigeria Drug Formulary. | G364: Use age/weight-based dosing according to the Nigeria Drug Formulary and pediatric guidance. | I364: =XLOOKUP(K364, pharmaceutical_index!B:B, pharmaceutical_index!A:A, "Not Found") | J364: Oxycodone | K364: Oxycodone | L364: Medicines used in substance dependence programmes | M364: Oxycodone
... A369: GN-00368 | B369: Pancuronium | C369: Anaesthetics, Preoperative Medicines And Medical Gases | D369: Skeletal muscle relaxants and cholinesterase inhibitors | E369: Listed in the Nigeria Essential Medicines List (NDF/EDL) for condition-specific treatment. | F369: Use strength- and indication-specific dosing as provided in the Nigeria Drug Formulary. | G369: Use age/weight-based dosing according to the Nigeria Drug Formulary and pediatric guidance. | I369: =XLOOKUP(K369, pharmaceutical_index!B:B, pharmaceutical_index!A:A, "Not Found") | J369: Pancuronium | K369: Pancuronium | L369: Skeletal muscle relaxants and cholinesterase inhibitors | M369: Pancuronium
A370: GN-00369 | B370: Pantothenic acid | C370: Vitamins, Minerals And Nutritionals | D370: General | E370: Listed in the Nigeria Essential Medicines List (NDF/EDL) for condition-specific treatment. | F370: Use strength- and indication-specific dosing as provided in the Nigeria Drug Formulary. | G370: Use age/weight-based dosing according to the Nigeria Drug Formulary and pediatric guidance. | H370: [object Object],[object Object],[object Object],[object Object] | I370: =XLOOKUP(K370, pharmaceutical_index!B:B, pharmaceutical_index!A:A, "Not Found") | J370: Pantothenic acid | K370: Pantothenic acid | L370: General | M370: Pantothenic acid
A371: GN-00370 | B371: Paracetamol | C371: Antimigraine Medicines | D371: For treatment of acute attack | E371: Listed in the Nigeria Essential Medicines List (NDF/EDL) for condition-specific treatment. | F371: Use strength- and indication-specific dosing as provided in the Nigeria Drug Formulary. | G371: Use age/weight-based dosing according to the Nigeria Drug Formulary and pediatric guidance. | I371: =XLOOKUP(K371, pharmaceutical_index!B:B, pharmaceutical_index!A:A, "Not Found") | J371: Paracetamol | K371: Paracetamol | L371: For treatment of acute attack | M371: Paracetamol
A372: GN-00371 | B372: Paraldehyde | C372: Anticonvulsants | D372: General | E372: Listed in the Nigeria Essential Medicines List (NDF/EDL) for condition-specific treatment. | F372: Use strength- and indication-specific dosing as provided in the Nigeria Drug Formulary. | G372: Use age/weight-based dosing according to the Nigeria Drug Formulary and pediatric guidance. | I372: =XLOOKUP(K372, pharmaceutical_index!B:B, pharmaceutical_index!A:A, "Not Found") | J372: Paraldehyde | K372: Paraldehyde | L372: General | M372: Paraldehyde
A373: GN-00372 | B373: Pegylated interferon alpha-2b | C373: Anti-Infective Medicines | D373: Other antivirals | E373: Listed in the Nigeria Essential Medicines List (NDF/EDL) for condition-specific treatment. | F373: Use strength- and indication-specific dosing as provided in the Nigeria Drug Formulary. | G373: Use age/weight-based dosing according to the Nigeria Drug Formulary and pediatric guidance. | I373: =XLOOKUP(K373, pharmaceutical_index!B:B, pharmaceutical_index!A:A, "Not Found") | J373: Pegylated interferon alpha-2b | K373: Pegylated interferon alpha-2b | L373: Other antivirals | M373: Pegylated interferon alpha-2b
A374: GN-00373 | B374: Pengrastrin | C374: Gastrointestinal Medicines | D374: Diagnostic agents for gastric function | E374: Listed in the Nigeria Essential Medicines List (NDF/EDL) for condition-specific treatment. | F374: Use strength- and indication-specific dosing as provided in the Nigeria Drug Formulary. | G374: Use age/weight-based dosing according to the Nigeria Drug Formulary and pediatric guidance. | I374: =XLOOKUP(K374, pharmaceutical_index!B:B, pharmaceutical_index!A:A, "Not Found") | J374: Pengrastrin | K374: Pengrastrin | L374: Diagnostic agents for gastric function | M374: Pengrastrin
A375: GN-00374 | B375: Pentamidine | C375: Anti-Infective Medicines | D375: Medicines for the treatment of first stage African trypanosomiasis | E375: Listed in the Nigeria Essential Medicines List (NDF/EDL) for condition-specific treatment. | F375: Use strength- and indication-specific dosing as provided in the Nigeria Drug Formulary. | G375: Use age/weight-based dosing according to the Nigeria Drug Formulary and pediatric guidance. | I375: =XLOOKUP(K375, pharmaceutical_index!B:B, pharmaceutical_index!A:A, "Not Found") | J375: Pentamidine | K375: Pentamidine | L375: Medicines for the treatment of first stage African trypanosomiasis | M375: Pentamidine
A376: GN-00375 | B376: Pentazocine | C376: Medicines For Pain And Palliative Care | D376: Narcotic analgesics | E376: Listed in the Nigeria Essential Medicines List (NDF/EDL) for condition-specific treatment. | F376: Use strength- and indication-specific dosing as provided in the Nigeria Drug Formulary. | G376: Use age/weight-based dosing according to the Nigeria Drug Formulary and pediatric guidance. | I376: =XLOOKUP(K376, pharmaceutical_index!B:B, pharmaceutical_index!A:A, "Not Found") | J376: Pentazocine | K376: Pentazocine | L376: Narcotic analgesics | M376: Pentazocine
A377: GN-00376 | B377: Permethrin | C377: Dermatological Medicines | D377: Scabicides and pediculicides | E377: Listed in the Nigeria Essential Medicines List (NDF/EDL) for condition-specific treatment. | F377: Use strength- and indication-specific dosing as provided in the Nigeria Drug Formulary. | G377: Use age/weight-based dosing according to the Nigeria Drug Formulary and pediatric guidance. | I377: =XLOOKUP(K377, pharmaceutical_index!B:B, pharmaceutical_index!A:A, "Not Found") | J377: Permethrin | K377: Permethrin | L377: Scabicides and pediculicides | M377: Permethrin
A378: GN-00377 | B378: Pethidine | C378: Medicines For Pain And Palliative Care | D378: Narcotic analgesics | E378: Listed in the Nigeria Essential Medicines List (NDF/EDL) for condition-specific treatment. | F378: Use strength- and indication-specific dosing as provided in the Nigeria Drug Formulary. | G378: Use age/weight-based dosing according to the Nigeria Drug Formulary and pediatric guidance. | I378: =XLOOKUP(K378, pharmaceutical_index!B:B, pharmaceutical_index!A:A, "Not Found") | J378: Pethidine | K378: Pethidine | L378: Narcotic analgesics | M378: Pethidine
A379: GN-00378 | B379: Phenobarbital | C379: Anticonvulsants + Anti-Epileptics | D379: General | E379: Listed in the Nigeria Essential Medicines List (NDF/EDL) for condition-specific treatment. | F379: Use strength- and indication-specific dosing as provided in the Nigeria Drug Formulary. | G379: Use age/weight-based dosing according to the Nigeria Drug Formulary and pediatric guidance. | I379: =XLOOKUP(K379, pharmaceutical_index!B:B, pharmaceutical_index!A:A, "Not Found") | J379: Phenobarbital | K379: Phenobarbital | L379: General | M379: Phenobarbital
A380: GN-00379 | B380: Phenoxymethylpenicillin | C380: Anti-Infective Medicines | D380: Antibacterial Medicine | E380: Listed in the Nigeria Essential Medicines List (NDF/EDL) for condition-specific treatment. | F380: Use strength- and indication-specific dosing as provided in the Nigeria Drug Formulary. | G380: Use age/weight-based dosing according to the Nigeria Drug Formulary and pediatric guidance. | I380: =XLOOKUP(K380, pharmaceutical_index!B:B, pharmaceutical_index!A:A, "Not Found") | J380: Phenoxymethylpenicillin | K380: Phenoxymethylpenicillin | L380: Antibacterial Medicine | M380: Phenoxymethylpenicillin
A381: GN-00380 | B381: Phenylephrine | C381: Ophthalmological Preparations | D381: Mydriatic medicines | E381: Listed in the Nigeria Essential Medicines List (NDF/EDL) for condition-specific treatment. | F381: Use strength- and indication-specific dosing as provided in the Nigeria Drug Formulary. | G381: Use age/weight-based dosing according to the Nigeria Drug Formulary and pediatric guidance. | I381: =XLOOKUP(K381, pharmaceutical_index!B:B, pharmaceutical_index!A:A, "Not Found") | J381: Phenylephrine | K381: Phenylephrine | L381: Mydriatic medicines | M381: Phenylephrine
A382: GN-00381 | B382: Phytomenadione (Vit K1) | C382: Antidotes And Other Substances Used In Poisonings | D382: Specific | E382: Listed in the Nigeria Essential Medicines List (NDF/EDL) for condition-specific treatment. | F382: Use strength- and indication-specific dosing as provided in the Nigeria Drug Formulary. | G382: Use age/weight-based dosing according to the Nigeria Drug Formulary and pediatric guidance. | I382: =XLOOKUP(K382, pharmaceutical_index!B:B, pharmaceutical_index!A:A, "Not Found") | J382: Phytomenadione | K382: Phytomenadione (Vit K1) | L382: Specific | M382: Phytomenadione
... A504: GN-00503 | B504: Vincristine | C504: Antineoplastic, Immunosuppressive Medicines And Adjuvants | D504: General | E504: Listed in the Nigeria Essential Medicines List (NDF/EDL) for condition-specific treatment. | F504: Use strength- and indication-specific dosing as provided in the Nigeria Drug Formulary. | G504: Use age/weight-based dosing according to the Nigeria Drug Formulary and pediatric guidance. | I504: =XLOOKUP(K504, pharmaceutical_index!B:B, pharmaceutical_index!A:A, "Not Found") | J504: Vincristine | K504: Vincristine | L504: General | M504: Vincristine
A505: GN-00504 | B505: Vitamin A | C505: Vitamins And Minerals | D505: General | E505: Listed in the Nigeria Essential Medicines List (NDF/EDL) for condition-specific treatment. | F505: Use strength- and indication-specific dosing as provided in the Nigeria Drug Formulary. | G505: Use age/weight-based dosing according to the Nigeria Drug Formulary and pediatric guidance. | H505: [object Object],[object Object],[object Object],[object Object],[object Object],[object Object],[object Object],[object Object],[object Object],[object Object] | I505: =XLOOKUP(K505, pharmaceutical_index!B:B, pharmaceutical_index!A:A, "Not Found") | J505: Vitamin A | K505: Vitamin A | L505: General | M505: Vitamin A
A506: GN-00505 | B506: Vitamin B complex | C506: Vitamins, Minerals And Nutritionals | D506: General | E506: Listed in the Nigeria Essential Medicines List (NDF/EDL) for condition-specific treatment. | F506: Use strength- and indication-specific dosing as provided in the Nigeria Drug Formulary. | G506: Use age/weight-based dosing according to the Nigeria Drug Formulary and pediatric guidance. | I506: =XLOOKUP(K506, pharmaceutical_index!B:B, pharmaceutical_index!A:A, "Not Found") | J506: Vitamin B complex | K506: Vitamin B complex | L506: General | M506: Vitamin B complex
A507: GN-00506 | B507: Vitamin B1 (Thiamine) | C507: Vitamins, Minerals And Nutritionals | D507: - 3.5 mg | E507: Listed in the Nigeria Essential Medicines List (NDF/EDL) for condition-specific treatment. | F507: Use strength- and indication-specific dosing as provided in the Nigeria Drug Formulary. | G507: Use age/weight-based dosing according to the Nigeria Drug Formulary and pediatric guidance. | H507: [object Object],[object Object],[object Object],[object Object],[object Object],[object Object],[object Object],[object Object] | I507: =XLOOKUP(K507, pharmaceutical_index!B:B, pharmaceutical_index!A:A, "Not Found") | J507: Vitamin B1 | K507: Vitamin B1 (Thiamine) | L507: - 3.5 mg | M507: Vitamin B1
A508: GN-00507 | B508: Vitamin B12 (Cyanocobalamin) | C508: Vitamins, Minerals And Nutritionals | D508: - 0.6 mg | E508: Listed in the Nigeria Essential Medicines List (NDF/EDL) for condition-specific treatment. | F508: Use strength- and indication-specific dosing as provided in the Nigeria Drug Formulary. | G508: Use age/weight-based dosing according to the Nigeria Drug Formulary and pediatric guidance. | H508: [object Object],[object Object],[object Object],[object Object],[object Object],[object Object] | I508: =XLOOKUP(K508, pharmaceutical_index!B:B, pharmaceutical_index!A:A, "Not Found") | J508: Vitamin B12 | K508: Vitamin B12 (Cyanocobalamin) | L508: - 0.6 mg | M508: Vitamin B12
A509: GN-00508 | B509: Vitamin B2 (Riboflavin) | C509: Vitamins, Minerals And Nutritionals | D509: - 1 mg | E509: Listed in the Nigeria Essential Medicines List (NDF/EDL) for condition-specific treatment. | F509: Use strength- and indication-specific dosing as provided in the Nigeria Drug Formulary. | G509: Use age/weight-based dosing according to the Nigeria Drug Formulary and pediatric guidance. | H509: [object Object],[object Object],[object Object],[object Object],[object Object],[object Object] | I509: =XLOOKUP(K509, pharmaceutical_index!B:B, pharmaceutical_index!A:A, "Not Found") | J509: Vitamin B2 | K509: Vitamin B2 (Riboflavin) | L509: - 1 mg | M509: Vitamin B2
A510: GN-00509 | B510: Vitamin B6 (Pyridoxine hydrochloride) | C510: Vitamins, Minerals And Nutritionals | D510: - 1 mg | E510: Listed in the Nigeria Essential Medicines List (NDF/EDL) for condition-specific treatment. | F510: Use strength- and indication-specific dosing as provided in the Nigeria Drug Formulary. | G510: Use age/weight-based dosing according to the Nigeria Drug Formulary and pediatric guidance. | H510: [object Object],[object Object],[object Object],[object Object],[object Object],[object Object],[object Object],[object Object] | I510: =XLOOKUP(K510, pharmaceutical_index!B:B, pharmaceutical_index!A:A, "Not Found") | J510: Vitamin B6 | K510: Vitamin B6 (Pyridoxine hydrochloride) | L510: - 1 mg | M510: Vitamin B6
A511: GN-00510 | B511: Vitamin C (Ascorbic acid) | C511: Vitamins And Minerals | D511: General | E511: Listed in the Nigeria Essential Medicines List (NDF/EDL) for condition-specific treatment. | F511: Use strength- and indication-specific dosing as provided in the Nigeria Drug Formulary. | G511: Use age/weight-based dosing according to the Nigeria Drug Formulary and pediatric guidance. | H511: [object Object],[object Object],[object Object],[object Object] | I511: =XLOOKUP(K511, pharmaceutical_index!B:B, pharmaceutical_index!A:A, "Not Found") | J511: Vitamin C | K511: Vitamin C (Ascorbic acid) | L511: General | M511: Vitamin C
A512: GN-00511 | B512: Vitamin D (Cholecalciferol) | C512: Vitamins, Minerals And Nutritionals | D512: - 2 micrograms | E512: Listed in the Nigeria Essential Medicines List (NDF/EDL) for condition-specific treatment. | F512: Use strength- and indication-specific dosing as provided in the Nigeria Drug Formulary. | G512: Use age/weight-based dosing according to the Nigeria Drug Formulary and pediatric guidance. | H512: [object Object],[object Object],[object Object],[object Object] | I512: =XLOOKUP(K512, pharmaceutical_index!B:B, pharmaceutical_index!A:A, "Not Found") | J512: Vitamin D | K512: Vitamin D (Cholecalciferol) | L512: - 2 micrograms | M512: Vitamin D
A513: GN-00512 | B513: Vitamin E | C513: Vitamins, Minerals And Nutritionals | D513: - 5 micrograms | E513: Listed in the Nigeria Essential Medicines List (NDF/EDL) for condition-specific treatment. | F513: Use strength- and indication-specific dosing as provided in the Nigeria Drug Formulary. | G513: Use age/weight-based dosing according to the Nigeria Drug Formulary and pediatric guidance. | H513: [object Object],[object Object],[object Object],[object Object],[object Object],[object Object] | I513: =XLOOKUP(K513, pharmaceutical_index!B:B, pharmaceutical_index!A:A, "Not Found") | J513: Vitamin E | K513: Vitamin E | L513: - 5 micrograms | M513: Vitamin E
A514: GN-00513 | B514: Warfarin | C514: Medicines Affecting The Blood | D514: Medicines affecting coagulation | E514: Listed in the Nigeria Essential Medicines List (NDF/EDL) for condition-specific treatment. | F514: Use strength- and indication-specific dosing as provided in the Nigeria Drug Formulary. | G514: Use age/weight-based dosing according to the Nigeria Drug Formulary and pediatric guidance. | I514: =XLOOKUP(K514, pharmaceutical_index!B:B, pharmaceutical_index!A:A, "Not Found") | J514: Warfarin | K514: Warfarin | L514: Medicines affecting coagulation | M514: Warfarin
A515: GN-00514 | B515: Xylometazoline | C515: Medicines For Ear, Nose And Throat | D515: General | E515: Listed in the Nigeria Essential Medicines List (NDF/EDL) for condition-specific treatment. | F515: Use strength- and indication-specific dosing as provided in the Nigeria Drug Formulary. | G515: Use age/weight-based dosing according to the Nigeria Drug Formulary and pediatric guidance. | I515: =XLOOKUP(K515, pharmaceutical_index!B:B, pharmaceutical_index!A:A, "Not Found") | J515: Xylometazoline | K515: Xylometazoline | L515: General | M515: Xylometazoline
A516: GN-00515 | B516: Yellow fever vaccine | C516: Immunologicals | D516: Vaccines | E516: Listed in the Nigeria Essential Medicines List (NDF/EDL) for condition-specific treatment. | F516: Use strength- and indication-specific dosing as provided in the Nigeria Drug Formulary. | G516: Use age/weight-based dosing according to the Nigeria Drug Formulary and pediatric guidance. | I516: =XLOOKUP(K516, pharmaceutical_index!B:B, pharmaceutical_index!A:A, "Not Found") | J516: Yellow fever vaccine | K516: Yellow fever vaccine | L516: Vaccines | M516: Yellow fever vaccine
A517: GN-00516 | B517: Zidovudine | C517: Anti-Infective Medicines | D517: Nucleoside + nucleotide reverse transcriptase inhibitors | E517: Listed in the Nigeria Essential Medicines List (NDF/EDL) for condition-specific treatment. | F517: Use strength- and indication-specific dosing as provided in the Nigeria Drug Formulary. | G517: Use age/weight-based dosing according to the Nigeria Drug Formulary and pediatric guidance. | I517: =XLOOKUP(K517, pharmaceutical_index!B:B, pharmaceutical_index!A:A, "Not Found") | J517: Zidovudine | K517: Zidovudine | L517: Nucleoside + nucleotide reverse transcriptase inhibitors | M517: Zidovudine
A518: GN-00517 | B518: Zidovudine + Lamivudine + Atazanavir + Ritonavir | C518: Unclassified | D518: General | E518: Listed in the Nigeria Essential Medicines List (NDF/EDL) for condition-specific treatment. | F518: Use strength- and indication-specific dosing as provided in the Nigeria Drug Formulary. | G518: Use age/weight-based dosing according to the Nigeria Drug Formulary and pediatric guidance. | I518: =XLOOKUP(K518, pharmaceutical_index!B:B, pharmaceutical_index!A:A, "Not Found") | J518: Zidovudine,Lamivudine,Atazanavir,Ritonavir | K518: Zidovudine + Lamivudine + Atazanavir + Ritonavir | L518: General | M518: Zidovudine, Lamivudine, Atazanavir, Ritonavir
A519: GN-00518 | B519: Zidovudine + Lamivudine + Efavirenz + Dolutegravir + Ritonavir | C519: Unclassified | D519: General | E519: Listed in the Nigeria Essential Medicines List (NDF/EDL) for condition-specific treatment. | F519: Use strength- and indication-specific dosing as provided in the Nigeria Drug Formulary. | G519: Use age/weight-based dosing according to the Nigeria Drug Formulary and pediatric guidance. | I519: =XLOOKUP(K519, pharmaceutical_index!B:B, pharmaceutical_index!A:A, "Not Found") | J519: Zidovudine,Lamivudine,Efavirenz,Dolutegravir,Ritonavir | K519: Zidovudine + Lamivudine + Efavirenz + Dolutegravir + Ritonavir | L519: General | M519: Zidovudine, Lamivudine, Efavirenz, Dolutegravir, Ritonavir
A520: GN-00519 | B520: Zidovudine + Lamivudine + Lopinavir + Ritonavir | C520: Unclassified | D520: General | E520: Listed in the Nigeria Essential Medicines List (NDF/EDL) for condition-specific treatment. | F520: Use strength- and indication-specific dosing as provided in the Nigeria Drug Formulary. | G520: Use age/weight-based dosing according to the Nigeria Drug Formulary and pediatric guidance. | I520: =XLOOKUP(K520, pharmaceutical_index!B:B, pharmaceutical_index!A:A, "Not Found") | J520: Zidovudine,Lamivudine,Lopinavir,Ritonavir | K520: Zidovudine + Lamivudine + Lopinavir + Ritonavir | L520: General | M520: Zidovudine, Lamivudine, Lopinavir, Ritonavir
A521: GN-00520 | B521: Zinc | C521: Gastrointestinal Medicines | D521: General | E521: Listed in the Nigeria Essential Medicines List (NDF/EDL) for condition-specific treatment. | F521: Use strength- and indication-specific dosing as provided in the Nigeria Drug Formulary. | G521: Use age/weight-based dosing according to the Nigeria Drug Formulary and pediatric guidance. | I521: =XLOOKUP(K521, pharmaceutical_index!B:B, pharmaceutical_index!A:A, "Not Found") | J521: Zinc | K521: Zinc | L521: General | M521: Zinc
A522: GN-00521 | B522: Zinc (sulfate) + Low Osmolarity Oral Rehydration Salts | C522: Unclassified | D522: General | E522: Listed in the Nigeria Essential Medicines List (NDF/EDL) for condition-specific treatment. | F522: Use strength- and indication-specific dosing as provided in the Nigeria Drug Formulary. | G522: Use age/weight-based dosing according to the Nigeria Drug Formulary and pediatric guidance. | I522: =XLOOKUP(K522, pharmaceutical_index!B:B, pharmaceutical_index!A:A, "Not Found") | J522: Zinc,Low Osmolarity Oral Rehydration Salts | K522: Zinc (sulfate) + Low Osmolarity Oral Rehydration Salts | L522: General | M522: Zinc, Low Osmolarity Oral Rehydration Salts
A523: GN-00522 | B523: Zinc chloride + zinc sulfate | C523: Dental Medicines | D523: Mouthwashes | E523: Listed in the Nigeria Essential Medicines List (NDF/EDL) for condition-specific treatment. | F523: Use strength- and indication-specific dosing as provided in the Nigeria Drug Formulary. | G523: Use age/weight-based dosing according to the Nigeria Drug Formulary and pediatric guidance. | I523: =XLOOKUP(K523, pharmaceutical_index!B:B, pharmaceutical_index!A:A, "Not Found") | J523: Zinc chloride,zinc sulfate | K523: Zinc chloride + zinc sulfate | L523: Mouthwashes | M523: Zinc chloride, zinc sulfate
A524: GN-00523 | B524: Zinc oxide | C524: Dermatological Medicines | D524: General | E524: Listed in the Nigeria Essential Medicines List (NDF/EDL) for condition-specific treatment. | F524: Use strength- and indication-specific dosing as provided in the Nigeria Drug Formulary. | G524: Use age/weight-based dosing according to the Nigeria Drug Formulary and pediatric guidance. | I524: =XLOOKUP(K524, pharmaceutical_index!B:B, pharmaceutical_index!A:A, "Not Found") | J524: Zinc oxide | K524: Zinc oxide | L524: General | M524: Zinc oxide
A525: GN-00524 | B525: Zinc oxide plaster | C525: Miscellaneous | D525: General | E525: Listed in the Nigeria Essential Medicines List (NDF/EDL) for condition-specific treatment. | F525: Use strength- and indication-specific dosing as provided in the Nigeria Drug Formulary. | G525: Use age/weight-based dosing according to the Nigeria Drug Formulary and pediatric guidance. | I525: =XLOOKUP(K525, pharmaceutical_index!B:B, pharmaceutical_index!A:A, "Not Found") | J525: Zinc oxide plaster | K525: Zinc oxide plaster | L525: General | M525: Zinc oxide plaster
... A1710: GN-1709 | B1710: Cenpai | C1710: Unclassified | D1710: General | E1710: General therapeutic or product use; verify indication in clinical reference. | F1710: Use dose according to product labeling and clinical guidance. | G1710: Use age/weight-appropriate dosing according to pediatric guidance. | I1710: =XLOOKUP(K1710, pharmaceutical_index!B:B, pharmaceutical_index!A:A, "Not Found") | J1710: Cenpai | K1710: Cenpai | L1710: General | M1710: Cenpai
B1711: drug_name | I1711: =XLOOKUP(K1711, pharmaceutical_index!B:B, pharmaceutical_index!A:A, "Not Found")
I1712: =XLOOKUP(K1712, pharmaceutical_index!B:B, pharmaceutical_index!A:A, "Not Found")

Sheet pharmaceutical_index
A1: code | B1: clinicalName | C1: drugClass | D1: pharmacology | E1: indications | F1: contraindications | G1: mechanism | H1: uuid | I1: sync_status | J1: sync_message | K1: sync_time
A2: PN-00001 | B2: Abacavir | C2: Nucleoside + nucleotide reverse transcriptase inhibitors | D2: NDF-listed pharmacologic agent used per formulation and approved indications. | E2: Condition-specific indications as defined in the Nigeria Drug Formulary. | F2: Contraindications include hypersensitivity and condition-specific restrictions in NDF guidance. | G2: Mechanism varies by active ingredient(s); refer to NDF therapeutic guidance for clinical use.
A3: PN-00002 | B3: Abacavir + Efavirenz + Lamivudine | C3: General | D3: NDF-listed pharmacologic agent used per formulation and approved indications. | E3: Condition-specific indications as defined in the Nigeria Drug Formulary. | F3: Contraindications include hypersensitivity and condition-specific restrictions in NDF guidance. | G3: Mechanism varies by active ingredient(s); refer to NDF therapeutic guidance for clinical use.
A4: PN-00003 | B4: Abacavir + Lamivudine | C4: Fixed-dose combinations (adult First line) | D4: NDF-listed pharmacologic agent used per formulation and approved indications. | E4: Condition-specific indications as defined in the Nigeria Drug Formulary. | F4: Contraindications include hypersensitivity and condition-specific restrictions in NDF guidance. | G4: Mechanism varies by active ingredient(s); refer to NDF therapeutic guidance for clinical use.
A5: PN-00004 | B5: Abiraterone | C5: General | D5: NDF-listed pharmacologic agent used per formulation and approved indications. | E5: Condition-specific indications as defined in the Nigeria Drug Formulary. | F5: Contraindications include hypersensitivity and condition-specific restrictions in NDF guidance. | G5: Mechanism varies by active ingredient(s); refer to NDF therapeutic guidance for clinical use.
A6: PN-00005 | B6: Acetic acid | C6: General | D6: NDF-listed pharmacologic agent used per formulation and approved indications. | E6: Condition-specific indications as defined in the Nigeria Drug Formulary. | F6: Contraindications include hypersensitivity and condition-specific restrictions in NDF guidance. | G6: Mechanism varies by active ingredient(s); refer to NDF therapeutic guidance for clinical use.
A7: PN-00006 | B7: Acetylcysteine | C7: Specific | D7: NDF-listed pharmacologic agent used per formulation and approved indications. | E7: Condition-specific indications as defined in the Nigeria Drug Formulary. | F7: Contraindications include hypersensitivity and condition-specific restrictions in NDF guidance. | G7: Mechanism varies by active ingredient(s); refer to NDF therapeutic guidance for clinical use.
A8: PN-00007 | B8: Acetylsalicylic acid | C8: Anti-platelet medicines | D8: NDF-listed pharmacologic agent used per formulation and approved indications. | E8: Condition-specific indications as defined in the Nigeria Drug Formulary. | F8: Contraindications include hypersensitivity and condition-specific restrictions in NDF guidance. | G8: Mechanism varies by active ingredient(s); refer to NDF therapeutic guidance for clinical use.
A9: PN-00008 | B9: Aciclovir | C9: Antiherpes medicines | D9: NDF-listed pharmacologic agent used per formulation and approved indications. | E9: Condition-specific indications as defined in the Nigeria Drug Formulary. | F9: Contraindications include hypersensitivity and condition-specific restrictions in NDF guidance. | G9: Mechanism varies by active ingredient(s); refer to NDF therapeutic guidance for clinical use.
A10: PN-00009 | B10: Actinomycin-D | C10: General | D10: NDF-listed pharmacologic agent used per formulation and approved indications. | E10: Condition-specific indications as defined in the Nigeria Drug Formulary. | F10: Contraindications include hypersensitivity and condition-specific restrictions in NDF guidance. | G10: Mechanism varies by active ingredient(s); refer to NDF therapeutic guidance for clinical use.
A11: PN-00010 | B11: Adalimumab | C11: General | D11: NDF-listed pharmacologic agent used per formulation and approved indications. | E11: Condition-specific indications as defined in the Nigeria Drug Formulary. | F11: Contraindications include hypersensitivity and condition-specific restrictions in NDF guidance. | G11: Mechanism varies by active ingredient(s); refer to NDF therapeutic guidance for clinical use.
A12: PN-00011 | B12: Albendazole | C12: Antifilarials | D12: NDF-listed pharmacologic agent used per formulation and approved indications. | E12: Condition-specific indications as defined in the Nigeria Drug Formulary. | F12: Contraindications include hypersensitivity and condition-specific restrictions in NDF guidance. | G12: Mechanism varies by active ingredient(s); refer to NDF therapeutic guidance for clinical use.
A13: PN-00012 | B13: Alfuzosin | C13: General | D13: NDF-listed pharmacologic agent used per formulation and approved indications. | E13: Condition-specific indications as defined in the Nigeria Drug Formulary. | F13: Contraindications include hypersensitivity and condition-specific restrictions in NDF guidance. | G13: Mechanism varies by active ingredient(s); refer to NDF therapeutic guidance for clinical use.
... A1710: PN-1709 | B1710: Cenpai | C1710: General | D1710: Pharmacology depends on active ingredient and formulation. | E1710: Indications depend on approved label and treatment guideline. | F1710: Contraindications include known hypersensitivity; verify label-specific risks. | G1710: Mechanism varies by active ingredient(s).
B1711: pharmaceutical_index_name
